Workbook

Sheet Read Me
A1: Read Me — Tab Guide & Legend
A2: Connect QA Gap Analysis · Web Platform stream
A4: TWO OUTPUTS OF THIS EXERCISE
A5: Output 1: MTP completeness | B5: Everything the product does that was NOT documented in this test plan. ALL functional gaps get added to the plan, whether or not engineering already tests them.
A6: Output 2: QA automation backlog | B6: The subset QA still needs to automate — the ones engineering does NOT already cover. Filter the Gap Analysis Action column for "Automate".
A8: TAB GUIDE (4 analysis tabs)
A9: Read Me | B9: This tab. The key to the workbook.
A10: Dashboard | B10: One-screen live dashboard: the two outputs (add-to-MTP / automate), dev + reconcile counts, AND the Coverage Tracker — per-surface automation % of existing MTP cases. Read this first.
A11: Gap Analysis (MAIN OUTPUT) | B11: Every coverage gap found — behaviour in the code with NO case in the test plan. Each row has its Bucket, Eng Coverage, and Action. Reviewers work here.
A12: Automation (existing MTP) | B12: The existing master test cases and their automation status: Green = already automated, Yellow = automatable-not-built, Red = manual-only. (This is the pass-1 baseline; the Dashboard Coverage Tracker rolls it up.)
A14: ORIGINAL TABS (not from this exercise)
A15: Test Tracker / Test Tracker Horizontal | B15: Pre-existing manual-execution trackers (run pass/fail). Left untouched.
A16: Surface tabs (Login, Opportunity creation, Visit verification, ...) | B16: The existing master test plan — documented cases by product area. The "before" picture the gap analysis was measured against.
A18: GAP ANALYSIS — 3 row types (by Gap ID prefix)
A19: Functional gap | B19: Behaviour in code with no MTP case. Core finding. IDs: GAP-SRC-*, GAP-BE-*, GAP-FE-*.
A20: Unit-test-coverage gap (dev) | B20: Where ENG code lacks a unit test. For dev teams. IDs: GAP-UTC-*.
A21: Cross-cutting | B21: Hygiene / MTP-vs-code discrepancy / automation note. IDs: GAP-MISC-*, GAP-MMISC-*.
A23: BUCKET column | B23: 🟢 Already automated · 🟡 Automatable-not-done (backlog) · 🔴 Manual only (real SMS/OTP/push/camera/device)
A24: ENG COVERAGE column | B24: Eng-covered (logic) = eng already tests it, QA e2e only if critical · QA-owned = eng cannot cover · Partial = confirm w/ eng · Eng GAP = eng missing a unit test · N/A
A25: ACTION column | B25: Add to MTP only (eng-covered) · Add to MTP + Automate (QA-owned) · Add to MTP + Automate (confirm w/ eng) · Dev: add unit test · Reconcile (plan/code)

Sheet Dashboard
A1: Dashboard — conclusions, outputs & coverage (live)
A3: CONCLUSIONS / ANALYSIS NOTES
A4: • Method: audited the master test plans against the actual product code to find behaviour with no test case (functional gaps), then cross-referenced each against engineering PR-run tests so QA does not duplicate eng work.
A5: • Two outputs: (1) MTP completeness = ALL functional gaps get added to the plan; (2) QA automation backlog = only the gaps eng does NOT already cover.
A6: • New gaps are mostly eng-covered: the majority of functional gaps found in code are already tested by eng at the logic layer -> add to MTP for completeness, but do NOT re-automate. QA new-automation shortlist is small (real device/SMS/push/cross-system).
A7: • Existing MTP backlog is the opposite: automatable-not-built existing cases are overwhelmingly UI / end-to-end journeys that eng unit tests do NOT cover -> this backlog genuinely needs QA automation (not duplicative of eng).
A8: • Net: eng-overlap savings land almost entirely on the NEW gaps, not the existing backlog. Manual-only (red) items stay manual regardless of framework.
A9: • All eng-coverage tags are best-guess from reading eng test structure, not verified line coverage - confirm the Partial items with the dev teams.
A11: OUTPUTS (from Gap Analysis)
A12: Output 1: functional gaps to ADD to MTP | B12: =COUNTIF('Gap Analysis'!$L:$L,"Add to MTP*")
A13: ...of which eng-covered (add to MTP only, do NOT automate) | B13: =COUNTIF('Gap Analysis'!$L:$L,"Add to MTP only*")
A14: Output 2: functional gaps to AUTOMATE (QA backlog) | B14: =COUNTIF('Gap Analysis'!$L:$L,"*Automate*")
A15: ...of which QA-owned (eng cannot cover) | B15: =COUNTIF('Gap Analysis'!$L:$L,"*QA-owned*")
A16: Dev: unit-test-coverage gaps | B16: =COUNTIF('Gap Analysis'!$L:$L,"Dev:*")
A17: Cross-cutting: reconcile plan/code | B17: =COUNTIF('Gap Analysis'!$L:$L,"Reconcile*")
A19: COVERAGE TRACKER — automation of existing MTP cases
A20: Surface | B20: Automated (built) | C20: Automatable (not built) | D20: Manual only | E20: Total | F20: % Automated
A21: Login page | B21: =COUNTIFS('Automation (existing MTP)'!$B:$B,$A21,'Automation (existing MTP)'!$D:$D,"🟢*") | C21: =COUNTIFS('Automation (existing MTP)'!$B:$B,$A21,'Automation (existing MTP)'!$D:$D,"🟡*") | D21: =COUNTIFS('Automation (existing MTP)'!$B:$B,$A21,'Automation (existing MTP)'!$D:$D,"🔴*") | E21: =B21+C21+D21 | F21: =IF(E21>0,B21/E21,0)
A22: Programs List page | B22: =COUNTIFS('Automation (existing MTP)'!$B:$B,$A22,'Automation (existing MTP)'!$D:$D,"🟢*") | C22: =COUNTIFS('Automation (existing MTP)'!$B:$B,$A22,'Automation (existing MTP)'!$D:$D,"🟡*") | D22: =COUNTIFS('Automation (existing MTP)'!$B:$B,$A22,'Automation (existing MTP)'!$D:$D,"🔴*") | E22: =B22+C22+D22 | F22: =IF(E22>0,B22/E22,0)
A23: Opportunity creation | B23: =COUNTIFS('Automation (existing MTP)'!$B:$B,$A23,'Automation (existing MTP)'!$D:$D,"🟢*") | C23: =COUNTIFS('Automation (existing MTP)'!$B:$B,$A23,'Automation (existing MTP)'!$D:$D,"🟡*") | D23: =COUNTIFS('Automation (existing MTP)'!$B:$B,$A23,'Automation (existing MTP)'!$D:$D,"🔴*") | E23: =B23+C23+D23 | F23: =IF(E23>0,B23/E23,0)
A24: Opportunity List page | B24: =COUNTIFS('Automation (existing MTP)'!$B:$B,$A24,'Automation (existing MTP)'!$D:$D,"🟢*") | C24: =COUNTIFS('Automation (existing MTP)'!$B:$B,$A24,'Automation (existing MTP)'!$D:$D,"🟡*") | D24: =COUNTIFS('Automation (existing MTP)'!$B:$B,$A24,'Automation (existing MTP)'!$D:$D,"🔴*") | E24: =B24+C24+D24 | F24: =IF(E24>0,B24/E24,0)
A25: Opportunity dashboard | B25: =COUNTIFS('Automation (existing MTP)'!$B:$B,$A25,'Automation (existing MTP)'!$D:$D,"🟢*") | C25: =COUNTIFS('Automation (existing MTP)'!$B:$B,$A25,'Automation (existing MTP)'!$D:$D,"🟡*") | D25: =COUNTIFS('Automation (existing MTP)'!$B:$B,$A25,'Automation (existing MTP)'!$D:$D,"🔴*") | E25: =B25+C25+D25 | F25: =IF(E25>0,B25/E25,0)
A26: Connect workers page | B26: =COUNTIFS('Automation (existing MTP)'!$B:$B,$A26,'Automation (existing MTP)'!$D:$D,"🟢*") | C26: =COUNTIFS('Automation (existing MTP)'!$B:$B,$A26,'Automation (existing MTP)'!$D:$D,"🟡*") | D26: =COUNTIFS('Automation (existing MTP)'!$B:$B,$A26,'Automation (existing MTP)'!$D:$D,"🔴*") | E26: =B26+C26+D26 | F26: =IF(E26>0,B26/E26,0)
A27: Visit verification page | B27: =COUNTIFS('Automation (existing MTP)'!$B:$B,$A27,'Automation (existing MTP)'!$D:$D,"🟢*") | C27: =COUNTIFS('Automation (existing MTP)'!$B:$B,$A27,'Automation (existing MTP)'!$D:$D,"🟡*") | D27: =COUNTIFS('Automation (existing MTP)'!$B:$B,$A27,'Automation (existing MTP)'!$D:$D,"🔴*") | E27: =B27+C27+D27 | F27: =IF(E27>0,B27/E27,0)
A28: Invoices List page | B28: =COUNTIFS('Automation (existing MTP)'!$B:$B,$A28,'Automation (existing MTP)'!$D:$D,"🟢*") | C28: =COUNTIFS('Automation (existing MTP)'!$B:$B,$A28,'Automation (existing MTP)'!$D:$D,"🟡*") | D28: =COUNTIFS('Automation (existing MTP)'!$B:$B,$A28,'Automation (existing MTP)'!$D:$D,"🔴*") | E28: =B28+C28+D28 | F28: =IF(E28>0,B28/E28,0)
A29: Connect Messaging | B29: =COUNTIFS('Automation (existing MTP)'!$B:$B,$A29,'Automation (existing MTP)'!$D:$D,"🟢*") | C29: =COUNTIFS('Automation (existing MTP)'!$B:$B,$A29,'Automation (existing MTP)'!$D:$D,"🟡*") | D29: =COUNTIFS('Automation (existing MTP)'!$B:$B,$A29,'Automation (existing MTP)'!$D:$D,"🔴*") | E29: =B29+C29+D29 | F29: =IF(E29>0,B29/E29,0)
A30: Delivery Reminder Mails | B30: =COUNTIFS('Automation (existing MTP)'!$B:$B,$A30,'Automation (existing MTP)'!$D:$D,"🟢*") | C30: =COUNTIFS('Automation (existing MTP)'!$B:$B,$A30,'Automation (existing MTP)'!$D:$D,"🟡*") | D30: =COUNTIFS('Automation (existing MTP)'!$B:$B,$A30,'Automation (existing MTP)'!$D:$D,"🔴*") | E30: =B30+C30+D30 | F30: =IF(E30>0,B30/E30,0)
A31: App Credentials | B31: =COUNTIFS('Automation (existing MTP)'!$B:$B,$A31,'Automation (existing MTP)'!$D:$D,"🟢*") | C31: =COUNTIFS('Automation (existing MTP)'!$B:$B,$A31,'Automation (existing MTP)'!$D:$D,"🟡*") | D31: =COUNTIFS('Automation (existing MTP)'!$B:$B,$A31,'Automation (existing MTP)'!$D:$D,"🔴*") | E31: =B31+C31+D31 | F31: =IF(E31>0,B31/E31,0)
A32: Re-Learn Task | B32: =COUNTIFS('Automation (existing MTP)'!$B:$B,$A32,'Automation (existing MTP)'!$D:$D,"🟢*") | C32: =COUNTIFS('Automation (existing MTP)'!$B:$B,$A32,'Automation (existing MTP)'!$D:$D,"🟡*") | D32: =COUNTIFS('Automation (existing MTP)'!$B:$B,$A32,'Automation (existing MTP)'!$D:$D,"🔴*") | E32: =B32+C32+D32 | F32: =IF(E32>0,B32/E32,0)
A33: Microplanning | B33: =COUNTIFS('Automation (existing MTP)'!$B:$B,$A33,'Automation (existing MTP)'!$D:$D,"🟢*") | C33: =COUNTIFS('Automation (existing MTP)'!$B:$B,$A33,'Automation (existing MTP)'!$D:$D,"🟡*") | D33: =COUNTIFS('Automation (existing MTP)'!$B:$B,$A33,'Automation (existing MTP)'!$D:$D,"🔴*") | E33: =B33+C33+D33 | F33: =IF(E33>0,B33/E33,0)
A34: TOTAL | B34: =SUM(B21:B33) | C34: =SUM(C21:C33) | D34: =SUM(D21:D33) | E34: =SUM(E21:E33) | F34: =IF(E34>0,B34/E34,0)
A36: EXISTING automatable-not-built cases — do they need automating?
A37: QA-owned (UI/e2e - need automating) | B37: =COUNTIF('Automation (existing MTP)'!$G:$G,"QA-owned (UI*")
A38: Likely already eng-covered (confirm - may NOT need automating) | B38: =COUNTIF('Automation (existing MTP)'!$G:$G,"Partial*")

Sheet Gap Analysis
A1: Gap ID | B1: Surface | C1: Description | D1: Bucket | E1: Rationale/Source | F1: Priority | G1: Status | H1: Assignee | I1: Reviewer's Notes | J1: Source | K1: Eng Coverage | L1: Action
A2: GAP-MISC-01 | B2: Cross-cutting | C2: Suite covers 'revoke suspension' (test_worker_visit_verification_page_03) but MTP has no such case - add to MTP | D2: 🟡 Automatable - not yet done | E2: Reverse gap: automated behaviour missing from MTP | F2: Medium | G2: New | J2: Pass 1: MTP vs test suite | K2: N/A (hygiene/discrepancy/automation note) | L2: Reconcile (plan/code)
A3: GAP-MISC-02 | B3: Cross-cutting | C3: Suite asserts Total-row count breakdown (test_worker_list_view_05) but MTP has no matching case - add to MTP | D3: 🟡 Automatable - not yet done | E3: Reverse gap: automated behaviour missing from MTP | F3: Medium | G3: New | J3: Pass 1: MTP vs test suite | K3: N/A (hygiene/discrepancy/automation note) | L3: Reconcile (plan/code)
A4: GAP-MISC-03 | B4: Cross-cutting | C4: test_worker_visit_verification_page_01_02 and _04_05_06_07 wrap assertions in bare try/except - tests can pass silently | D4: 🟡 Automatable - not yet done | E4: Suite quality: assertions swallowed; fix in automation repo | F4: High | G4: New | J4: Pass 1: MTP vs test suite | K4: N/A (hygiene/discrepancy/automation note) | L4: Reconcile (plan/code)
A5: GAP-MISC-04 | B5: Cross-cutting | C5: Allure tags/descriptions reference an older MTP numbering (e.g. suite OLP_1 = opportunity creation vs current MTP OLP_01 = landing page) - IDs need reconciliation | D5: 🟡 Automatable - not yet done | E5: Suite/MTP ID drift discovered in pass 1 | F5: High | G5: New | J5: Pass 1: MTP vs test suite | K5: N/A (hygiene/discrepancy/automation note) | L5: Reconcile (plan/code)
A6: GAP-MISC-05 | B6: Cross-cutting | C6: MTP has duplicate case ID OD_18 (learn/deliver apps info AND inactive-workers pre-filter) | D6: 🟡 Automatable - not yet done | E6: MTP hygiene: duplicate ID to fix on sheet | F6: Medium | G6: New | J6: Pass 1: MTP vs test suite | K6: N/A (hygiene/discrepancy/automation note) | L6: Reconcile (plan/code)
A7: GAP-MISC-06 | B7: Cross-cutting | C7: MTP rows without case IDs: Connect-worker search case, OLP_05 PM-user variant, Microplanning core-metrics download case | D7: 🟡 Automatable - not yet done | E7: MTP hygiene: assign IDs so cases are trackable | F7: Medium | G7: New | J7: Pass 1: MTP vs test suite | K7: N/A (hygiene/discrepancy/automation note) | L7: Reconcile (plan/code)
A8: GAP-SRC-W-01 | B8: Visit verification page | C8: Audio attachments on visits with server-side transcription + translation (AudioAttachment.transcript/translation; audio_attachment/<pk>/transcribe endpoint) | D8: 🟡 Automatable - not yet done | E8: MISSING from MTP (WVV covers image carousel only, not audio/transcription). Src: opportunity AudioAttachment + AudioAttachmentTranscribe | F8: High | G8: New | J8: Web pass 4/5 batch 1: commcare-connect opportunity spine (urls+models) | K8: Partial (some eng coverage; confirm with eng) | L8: Add to MTP + Automate (confirm w/ eng)
A9: GAP-SRC-W-02 | B9: Visit verification page | C9: Granular verification-flag types configured per opportunity: gps, duplicate, location-radius, form-submission time window (start/end), catchment_areas, duration | D9: 🟡 Automatable - not yet done | E9: PARTIAL vs OD_7 (generic 'verification flags'). Each flag type not a case. Src: OpportunityVerificationFlags model | F9: High | G9: New | J9: Web pass 4/5 batch 1: commcare-connect opportunity spine (urls+models) | K9: Eng-covered (logic) - QA e2e only if critical journey | L9: Add to MTP only (eng-covered)
A10: GAP-SRC-W-03 | B10: Visit verification page | C10: Catchment-area based verification: import/export catchment areas (CSV) and flag visits outside the area (CatchmentArea model, import/export_catchment_area) | D10: 🟡 Automatable - not yet done | E10: MISSING from MTP. Src: opportunity CatchmentArea + import_catchment_area/export_catchment_area | F10: Medium | G10: New | J10: Web pass 4/5 batch 1: commcare-connect opportunity spine (urls+models) | K10: Partial (some eng coverage; confirm with eng) | L10: Add to MTP + Automate (confirm w/ eng)
A11: GAP-SRC-W-04 | B11: Visit verification page | C11: Form-JSON validation rules (question path == value) and per-deliver-unit flag rules (check_attachments, duration) as configurable verification checks | D11: 🟡 Automatable - not yet done | E11: MISSING from MTP. Src: FormJsonValidationRules + DeliverUnitFlagRules + delete_form_json_rule | F11: Medium | G11: New | J11: Web pass 4/5 batch 1: commcare-connect opportunity spine (urls+models) | K11: Eng-covered (logic) - QA e2e only if critical journey | L11: Add to MTP only (eng-covered)
A12: GAP-SRC-W-05 | B12: Opportunity creation | C12: auto_approve_payments opportunity setting (distinct from auto_approve_visits) - payments auto-approved without manual step | D12: 🟡 Automatable - not yet done | E12: MISSING from MTP (visit auto-approve covered, payment auto-approve not). Src: Opportunity.auto_approve_payments | F12: Medium | G12: New | J12: Web pass 4/5 batch 1: commcare-connect opportunity spine (urls+models) | K12: Eng-covered (logic) - QA e2e only if critical journey | L12: Add to MTP only (eng-covered)
A13: GAP-SRC-W-06 | B13: Opportunity creation | C13: automatic_visit_verification opportunity flag (system auto-verifies visits against rules, distinct from NM manual approve) | D13: 🟡 Automatable - not yet done | E13: PARTIAL vs MTP. Src: Opportunity.automatic_visit_verification | F13: Medium | G13: New | J13: Web pass 4/5 batch 1: commcare-connect opportunity spine (urls+models) | K13: Eng-covered (logic) - QA e2e only if critical journey | L13: Add to MTP only (eng-covered)
... A65: GAP-SRC-W-52 | B65: Connect workers page | C65: Payments tab specifics: only rows with payment_accrued>=0 and accepted=True, ordered -payment_accrued; Accrued/Total Paid/Confirm headers are currency-code-suffixed and blank when no rows; footers sum accrued and total paid; last-paid history is a lazy popup ('--' when never paid); payment import is CSV/XLSX-only and cache-locked against concurrent imports. Src: WorkerPaymentsView (~2794-2820); WorkerPaymentsTable (~1173-1229); payment_import (~784-802). | D65: 🟡 Automatable - not yet done | E65: PARTIAL vs Payment Processing_1-4 (info/pay/history/rollback happy path). | F65: Low | G65: New | J65: Web pass 7: workers-page views/tables/filters/templates deep-dive (feature/workers-web-automation) | K65: Eng-covered (logic) - QA e2e only if critical journey | L65: Add to MTP only (eng-covered)

Sheet Automation (existing MTP)
A1: Case / Gap ID | B1: Surface | C1: Description | D1: Status | E1: Detail | F1: Source | G1: Eng Coverage
A2: PLP_05 | B2: Programs List page | C2: Verify that the ‘Program Acceptance Funnel’ within a program card has all the necessary information in it | D2: 🟢 Already automated | E2: test_pm_05_06_07 | F2: Confirmed automated (pass 1) | G2: Already automated (n/a)
A3: PLP_06 | B3: Programs List page | C3: Confirm user is able to see the status of all the NMs that they invited | D3: 🟢 Already automated | E3: test_pm_05_06_07 | F3: Confirmed automated (pass 1) | G3: Already automated (n/a)
A4: PLP_07 | B4: Programs List page | C4: Verify that user is only able to create/view opportunities when at least one NM has accepted the invite | D4: 🟢 Already automated | E4: test_pm_05_06_07 | F4: Confirmed automated (pass 1) | G4: Already automated (n/a)
A5: Opp_create_04 | B5: Opportunity creation | C5: Verify user is able to create on opportunity as PM user | D5: 🟢 Already automated | E5: test_olp_01_02_03 | F5: Confirmed automated (pass 1) | G5: Already automated (n/a)
A6: Opp_create_05 | B6: Opportunity creation | C6: Verify user is able to land on the payment unit page | D6: 🟢 Already automated | E6: test_olp_01_02_03 | F6: Confirmed automated (pass 1) | G6: Already automated (n/a)
A7: Opp_create_21 | B7: Opportunity creation | C7: Verify user is able to land on the Budget page | D7: 🟢 Already automated | E7: test_olp_01_02_03 | F7: Confirmed automated (pass 1) | G7: Already automated (n/a)
A8: Opp_create_28 | B8: Opportunity creation | C8: Verify user is able to create the opportunity successfully | D8: 🟢 Already automated | E8: test_olp_01_02_03 | F8: Confirmed automated (pass 1) | G8: Already automated (n/a)
A9: OLP_11 | B9: Opportunity List page | C9: Verify "Status" field drop down contains: - Active - Ended - Inactive | D9: 🟢 Already automated | E9: test_olp_11 | F9: Confirmed automated (pass 1) | G9: Already automated (n/a)
A10: OD_2 | B10: Opportunity dashboard | C10: Confirm user can see the opportunity details on the dashboard page | D10: 🟢 Already automated | E10: test_olp_04 | F10: Confirmed automated (pass 1) | G10: Already automated (n/a)
A11: OD_4 | B11: Opportunity dashboard | C11: Verify user see the all the information related to the deliveries under "Service Deliveries" section | D11: 🟢 Already automated | E11: test_olp_05 | F11: Confirmed automated (pass 1) | G11: Already automated (n/a)
A12: OD_5 | B12: Opportunity dashboard | C12: Verify user can see all the payment related information under "Payments to Workers" section | D12: 🟢 Already automated | E12: test_olp_06 | F12: Confirmed automated (pass 1) | G12: Already automated (n/a)
... A339: Connect_worker_13 | B339: Connect workers page | C339: Verify user is able to delete not-found users (Delete affordance; not executed to preserve seed) | D339: 🟢 Already automated | E339: test_worker_lifecycle.py::test_connect_worker_13_not_found_deletable | F339: Connect Workers Batch C - Anshu data 2 (Worker_Lifecycle_Automation, 2026-09-10) | G339: Already automated (n/a)

Sheet  Test Tracker
B1: CCC Web Platform [Master] | F1: Keys
F2: Pass | H2: Passed steps of Test Case
F3: Fail | H3: Failed steps of Test Case
F4: N/A | H4: Not applicable to your testing
F5: Blocking | H5: Failed and is a critical feature or cannot proceed with testing
A6: Name of Tester | B6: Start Date | C6: End Date | F6: Unanswered | H6: Unanswered/ blank test cases
A9: Tab | B9: Execution Status | C9: Duration (In Hours) | D9: Comments (if any) | F9: Case Results (if none, displays as 0) | K9: Total | M9: Ticket Summaries (if none, displays as #N/A)
A10: =sheetName(2) | F10: =countif(INDIRECT("'"&A10&"'!"&"F2:F1000"), "Pass") | G10: =countif(INDIRECT("'"&A10&"'!"&"F2:F1000"), "Fail") | H10: =countif(INDIRECT("'"&A10&"'!"&"F2:F1000"), "N/A") | I10: =countif(INDIRECT("'"&A10&"'!"&"F2:F1000"), "Blocking") | J10: =countif(INDIRECT("'"&A10&"'!"&"F2:F1000"), "") | K10: =sum(F10:J10) | M10: =IFERROR(__xludf.DUMMYFUNCTION(" TRANSPOSE(UNIQUE( FILTER( INDIRECT(""'""&A10&""'!""&""G3:G200"") , NOT(ISBLANK(INDIRECT(""'""&A10&""'!""&""G3:G200""))) ) ))"),"#N/A")
A11: =sheetName(3) | F11: =countif(INDIRECT("'"&A11&"'!"&"F2:F1000"), "Pass") | G11: =countif(INDIRECT("'"&A11&"'!"&"F2:F1000"), "Fail") | H11: =countif(INDIRECT("'"&A11&"'!"&"F2:F1000"), "N/A") | I11: =countif(INDIRECT("'"&A11&"'!"&"F2:F1000"), "Blocking") | J11: =countif(INDIRECT("'"&A11&"'!"&"F2:F1000"), "") | K11: =sum(F11:J11)
A12: =sheetName(4) | F12: =countif(INDIRECT("'"&A12&"'!"&"F2:F1000"), "Pass") | G12: =countif(INDIRECT("'"&A12&"'!"&"F2:F1000"), "Fail") | H12: =countif(INDIRECT("'"&A12&"'!"&"F2:F1000"), "N/A") | I12: =countif(INDIRECT("'"&A12&"'!"&"F2:F1000"), "Blocking") | J12: =countif(INDIRECT("'"&A12&"'!"&"F2:F1000"), "") | K12: =sum(F12:J12)
A13: =sheetName(5) | F13: =countif(INDIRECT("'"&A13&"'!"&"F2:F1000"), "Pass") | G13: =countif(INDIRECT("'"&A13&"'!"&"F2:F1000"), "Fail") | H13: =countif(INDIRECT("'"&A13&"'!"&"F2:F1000"), "N/A") | I13: =countif(INDIRECT("'"&A13&"'!"&"F2:F1000"), "Blocking") | J13: =countif(INDIRECT("'"&A13&"'!"&"F2:F1000"), "") | K13: =sum(F13:J13)
A14: =sheetName(3) | F14: =countif(INDIRECT("'"&A14&"'!"&"F2:F1000"), "Pass") | G14: =countif(INDIRECT("'"&A14&"'!"&"F2:F1000"), "Fail") | H14: =countif(INDIRECT("'"&A14&"'!"&"F2:F1000"), "N/A") | I14: =countif(INDIRECT("'"&A14&"'!"&"F2:F1000"), "Blocking") | J14: =countif(INDIRECT("'"&A14&"'!"&"F2:F1000"), "") | K14: =sum(F14:J14)
A15: =sheetName(7) | F15: =countif(INDIRECT("'"&A15&"'!"&"F2:F1000"), "Pass") | G15: =countif(INDIRECT("'"&A15&"'!"&"F2:F1000"), "Fail") | H15: =countif(INDIRECT("'"&A15&"'!"&"F2:F1000"), "N/A") | I15: =countif(INDIRECT("'"&A15&"'!"&"F2:F1000"), "Blocking") | J15: =countif(INDIRECT("'"&A15&"'!"&"F2:F1000"), "") | K15: =sum(F15:J15)
A16: =sheetName(8) | F16: =countif(INDIRECT("'"&A16&"'!"&"F2:F1000"), "Pass") | G16: =countif(INDIRECT("'"&A16&"'!"&"F2:F1000"), "Fail") | H16: =countif(INDIRECT("'"&A16&"'!"&"F2:F1000"), "N/A") | I16: =countif(INDIRECT("'"&A16&"'!"&"F2:F1000"), "Blocking") | J16: =countif(INDIRECT("'"&A16&"'!"&"F2:F1000"), "") | K16: =sum(F16:J16)
A17: =sheetName(9) | F17: =countif(INDIRECT("'"&A17&"'!"&"F2:F1000"), "Pass") | G17: =countif(INDIRECT("'"&A17&"'!"&"F2:F1000"), "Fail") | H17: =countif(INDIRECT("'"&A17&"'!"&"F2:F1000"), "N/A") | I17: =countif(INDIRECT("'"&A17&"'!"&"F2:F1000"), "Blocking") | J17: =countif(INDIRECT("'"&A17&"'!"&"F2:F1000"), "") | K17: =sum(F17:J17)
A18: =sheetName(10) | F18: =countif(INDIRECT("'"&A18&"'!"&"F2:F1000"), "Pass") | G18: =countif(INDIRECT("'"&A18&"'!"&"F2:F1000"), "Fail") | H18: =countif(INDIRECT("'"&A18&"'!"&"F2:F1000"), "N/A") | I18: =countif(INDIRECT("'"&A18&"'!"&"F2:F1000"), "Blocking") | J18: =countif(INDIRECT("'"&A18&"'!"&"F2:F1000"), "") | K18: =sum(F18:J18)
A19: =sheetName(11) | F19: =countif(INDIRECT("'"&A19&"'!"&"F2:F1000"), "Pass") | G19: =countif(INDIRECT("'"&A19&"'!"&"F2:F1000"), "Fail") | H19: =countif(INDIRECT("'"&A19&"'!"&"F2:F1000"), "N/A") | I19: =countif(INDIRECT("'"&A19&"'!"&"F2:F1000"), "Blocking") | J19: =countif(INDIRECT("'"&A19&"'!"&"F2:F1000"), "") | K19: =sum(F19:J19)
A20: =sheetName(12) | F20: =countif(INDIRECT("'"&A20&"'!"&"F2:F1000"), "Pass") | G20: =countif(INDIRECT("'"&A20&"'!"&"F2:F1000"), "Fail") | H20: =countif(INDIRECT("'"&A20&"'!"&"F2:F1000"), "N/A") | I20: =countif(INDIRECT("'"&A20&"'!"&"F2:F1000"), "Blocking") | J20: =countif(INDIRECT("'"&A20&"'!"&"F2:F1000"), "") | K20: =sum(F20:J20)
A21: =sheetName(13)

Sheet Login page
A1: Test Case ID | B1: Description | C1: Steps | D1: Outcome | E1: Status (Pass/Fail) | F1: QA Ticket | G1: Comments
A2: Login Page
A3: Login 1 | B3: Verify user sees the username and password fields on the login page | C3: 1. Click on the link: https://connect-staging.dimagi.com/accounts/login | D3: - User should see the two fields for password and username on the login page - User should be able to input any value in the fields - User should see a Login button - User should also see Reset password button
A4: Login 2 | B4: Verify the fields accept the correct inputs only | C4: 1. Navigate to CCC login page 2. enter the username and password | D4: - The username field should show the appropriate error messages if user enters email in wrong format - We should display placeholder text in the fields for users
A5: Login 3 | B5: Verify user can login by entering the correct credentials | C5: cont to above TC - Click on login button | D5: - User should be able to login with the right creds - User should not be able to login with wrong credentials
A6: Login 4 | B6: User should be able to login using CommCare HQ login option i.e. SSO | C6: 1.Navigate to CCC web login page 2.Click on login with commcare 3. Authorize the commcare 4. You will be login to CCC web
A7: Login 5 | B7: Verify if the user see a sign-up option | C7: 1. On CCC web login page, click on the sign up link at the bottom 2. Create a CCC account | D7: - User should be taken to the sign up page on clicking the sign up button
A8: Login 6 | B8: Ensure user is unable to login using the wrong credentials on the login page | C8: 1. Go to CCC login page 2. Enter wrong username and password 3. Click login button | D8: - User should see an appropriate error message if they try to login using wrong creds
A9: Login 7 | B9: User should be prompted to login on HQ if they use Login via CommCare HQ option | C9: Cont to above TC - On account creation page, Click on Signup with commcare HQ | D9: - User should be taken to HQ login page if they try to login using CommCare HQ and they are not logged in on HQ
A10: Login 8 | B10: User should be able to reset password for their account | C10: 1. Navigate to CCC web UI login page 2. Click on reset password link | D10: On clicking the reset button, user should be able to initiate the reset password flow to reset the account password
A11: Login 9 | B11: User should be able to login with the new password | C11: 1. Login with new password into the CCC web UI | D11: User should be able to login with the new password after resetting the pw

Sheet Programs List page
A1: Test Case ID | B1: Description | C1: Steps | D1: Outcome | E1: Status (Pass/Fail) | F1: QA Ticket | G1: Comments
A2: PLP_01 | B2: Verify user is able to create new program | C2: 1. Login to CCC web UI as PM user 2. Click on +Add Programs button 3. Fill the following details: - Name - Description - Select delivery type - Budget - Currency - Country - Start date - End date 4. Click submit | D2: - User is able to create new program successfully - Created program is shown on the programs list page | E2: Pass | G2: Automated (setup flow: create_program)
A3: PLP_02 | B3: Confirm that the user is able to invite NMs to the program that they created | C3: cont from above TC - Invite NM user to a program | D3: User should be able to invite the NMs to the programs | E3: Pass | G3: Automated (setup flow: invite_network_manager)
A4: PLP_03 | B4: Confirm PM sees all the programs on the dashboard screen | C4: 1. Log in to CCC web UI 2. Click on the hamburger option present on left side 3. Select the programs option | D4: - PM user should be able to view all the programs as separate cards - The programs should be sorted by the most recent program creation date - Each program card should display the relevant summary to the PM: i) Program description ii) Start and End date iii) Budget allocated | E4: Pass | G4: Automated: test_plp_list_page (card summary fields)
A5: PLP_04 | B5: Confirm user is able to select any of the programs from the list | D5: - User should be able to select any program from the list - User should be able to perform any of the following action after selecting the program i) View the ‘Program Acceptance Funnel’ ii) View the Status of the Program by clicking the ‘View Status’ button and expanding out more information iii) Invite new Network Managers using the Invite button | E5: Pass | G5: Automated: test_plp_list_page (View Status expand)
A6: PLP_05 | B6: Verify that the ‘Program Acceptance Funnel’ within a program card has all the necessary information in it | C6: 1. Login to CCC web UI 2. Navigate to programs list page 3. Click on view status button on the program details | D6: The ‘Program Acceptance Funnel’ should have the following information - Number of Network Managers Invited - Number Applied - Number Accepted | E6: Pass | G6: Automated: test_plp_list_page (acceptance_funnel)
A7: PLP_06 | B7: Confirm user is able to see the status of all the NMs that they invited | C7: 1. Login to CCC web UI 2. Navigate to programs list page 3. Click on view status button on the program details | D7: - User should be able to see the status of the NMs invited by clicking the 'View Status' button and expand the list of Network Managers - The list should display all the NM Orgs under a Program should be listed in alphabetical order for consistency of view - For each NM, user should be able to see the status as Invited, Applied or Accepted | E7: Pass | G7: Automated: test_plp_list_page (nm_application_statuses)
A8: PLP_07 | B8: Verify that user is only able to create/view opportunities when at least one NM has accepted the invite | C8: 1. Login to CCC web UI 2. Navigate to programs list page 3. Click on view status button on the program details 4. Click on create opportunity for creating new opportunity 5. Click on view opportunity for viewing the opportunities | D8: Only when an NM is in accepted status, user should be able to take either of the following actions as a next step - Create Opportunity - View Opportunity | E8: Pass | G8: Automated (setup flow: Create/View Opportunity when accepted)
A9: PLP_08 | B9: Verify on landing the Program page, user is able work on the program | D9: When the user land on the Program page,they should be able to perform any of the two actions: - Reviewing visits approved by NMs - Paying invoices | G9: Not on list page; = Recent Activities destinations (link targets asserted)
A10: PLP_09 | B10: Verify on landing the Opportunity page, user is able check the performance of the program | D10: User should be able to compare the performance of different NMs through the following fields - Active Workers - Deliveries - Approved Deliveries - Earnings User should be able to go through the opportunity dashboard as to check how the workers are performing | G10: Covered via Opportunity List PM columns (test_olp_list_page)
A11: PLP_10 | B11: Confirm user see following information for any program in the list - Program Name - Program Manager Org Name -Delivery Type - Program Start Date - Program End Date - Status: Invited or Applied or Accepted | D11: - User should see all the information for the program in the list - The accepted status appears after Opportunity creation, so confirm that as well | E11: Pass | G11: Automated: test_plp_list_page (card summary fields)
A12: PLP_11 | B12: User should be able to click on "View Opportunities" button in a program to view opportunities | C12: 1.Login to CCC web UI 2. Navigate to program list page 3. Click on view status dropdown on program details section 4. Click on view opportunities button | D12: - If there are any opportunities in a program, user should be able to see the list of all opportunities by clicking the button | E12: Pass | G12: Automated: test_plp_list_page (click_view_opportunities)
A13: PLP_12 | B13: On the right panel, user should see the following three options - Pending Review - Pending Payment - Inactive Workers | D13: - On clicking the category, the Program Name/Opportunities are listed based on descending order of the relevant metric - The number of items in the list should be restricted to 3 per category | E13: Pass | G13: Automated: test_plp_list_page (Recent Activities categories + rows)
A14: PLP_14 | B14: Verify when user clicks on 'Pending Payments', they see a list of opportunities with pending payments | C14: 1.Login to CCC web UI 2. Navigate to program list page 3. Click on the opportunity under pending payments section | D14: - When user clicks on the pending payments option on the right pane, user should see a list of opportunities with pending payments - When user clicks on an Opportunity under ‘Pending Payments’, they should jump to the Worker List page with the payment tab open | E14: Pass | G14: Automated (link target asserted): Recent Activities row hrefs
A15: PLP_15 | B15: Verify user can see all the workers who have not delivered any visits or not completed any learning in last 3 days when they click on Inactive Workers option | C15: 1.Login to CCC web UI 2. Navigate to program list page 3. Click on the opportunity under inactive workers section | D15: - When user clicks on 'Inactive Workers' option, user should see a list of opportunities with inactive workers - When user clicks on an Opportunity under ‘Inactive Workers’, they should jump to the Worker List page with the filtered list of workers who have not delivered any visits or not completed a learning module in the last 3 days. | E15: Pass | G15: Automated (link target asserted): Recent Activities row hrefs
A16: PLP_16 | B16: Confirm when user clicks on Apply button for any program, the PM can see the user have applied | C16: 1. Login to CCC web UI as NM user 2. Navigate to programs list page 3. Click on apply for a program 4. Switch to PM user account 5. Verify on programs list page | D16: - Program manager should be able to see if someone applies for a program | E16: Pass | G16: Automated (setup flow: apply_to_program)
A17: PLP_17 | B17: Verify that the user can view opportunities associated with a specific NM user by clicking the 'View Opportunities' button on the Program List page. [PM user] | C17: 1. Login to CCC web UI 2. Navigate to program list page 3. Click on view status dropdown for any program 4. Click on view opportunities button for any NM user under a program | D17: - User is able to see the opportunities related to specific NM user | E17: Pass | G17: Automated: test_plp_list_page (View Opportunities)

Sheet Opportunity creation
A1: Test Case ID | B1: Description | C1: Steps | D1: Outcome | E1: Status (Pass/Fail) | F1: QA Ticket | G1: Comments
A2: Opp_create_01 | B2: Confirm user is not able to create an opportunity as NM user | D2: -User is not able to create an opportunity as NM user
A3: Opp_create_02 | B3: Verify user is not able to create non managed opp as PM user | D3: - User is not able to create a non managed Opportunity as PM user
A4: Opp_create_03 | B4: Verify all the non managed opp are linked to legacy test program | D4: - All non managed opp are migrated to managed opps and linked legacy test program
A5: Opp_create_04 | B5: Verify user is able to create on opportunity as PM user | C5: 1. Login to CCC web UI 2. Navigate to program list page 3. Under a program click on view status >> Under NM user details click on create opportunity button 4. Fill all the required details - Select the NM user from drop down - Enter name, short description and Description - Select the currency from dropdown - Select the required server from the "HQ server" dropdown - Select the api key from "API key" dropdown - Under apps section, select the domain and learn/deliver apps from their respective dropdowns - Enter learn app description and learn app passing score 5. Click submit | D5: - User should land on the create opportunity page - When hq server is selected, the api keys related to the selected hq server are dispalyed in the dropdown - Domain dropdowns displays the domains that related to the selected api key - Apps that belongs to the selected domain are displayed in the dropdown
A6: Opp_create_05 | B6: Verify user is able to land on the payment unit page | C6: Continue to above TC 6. On payment unit page, Click Add payment unit 7. payment unit create section is appeared 8. Fill all the required fileds - Enter payment name and description - Enter the amount that will accured per visit - Enter amount for org per visit - Enter the number of Max.total visits that a worker should be able to submit overall - Enter number of Max.daily visits that a work should be able to submit per day - Enter start and end date Under required details section, select the deliver units [ Payment is accured only when selected forms are submitted and approved] 9. Click "Setup budget" | D6: - User should land on the payment unit page - USer should be able to add payment units for an opportunity
A7: Opp_create_06 | B7: Verify user can set Org Pay at the payment unit level. | C7: 1. Login to CCC web UI as PM user 2. Create a managed opportunity 3. Click submit 4. On payment unit page, verify we can see org pay field 5. Enter the amount and fill all the fields 6. Set up budget | D7: - User should be to set Org pay at payment unit level
A8: Opp_create_07 | B8: Verify Org Pay can be configured independently for each payment unit within the same opportunity. | C8: 1.Login as PM user 2.Create opportunity with multiple payment units 3.Set Org Pay for Payment Unit 1 (e.g., 50) 4.Set a different Org Pay for Payment Unit 2 (e.g., 75) 5. Click save | D8: - User should configure org pay independently for each payment
A9: Opp_create_08 | B9: Verify editing Org Pay for one payment unit does not affect others. | C9: 1.Open an existing opportunity with multiple payment units 2.Edit Org Pay of Payment Unit 1 3.Save and refresh 4.Verify Org Pay of other units | D9: - Editing the payment unit should not effect the other payment units
A10: Opp_create_09 | B10: Verify payment units can be configured with 0 Org Pay | C10: 1.Add a payment unit 2. Set Org Pay = 0 3. Save changes | D10: - User should be able to configure zero org pay payments - User should be able to submit the forms for zero org payment units
A11: Opp_create_10 | B11: Verify valid error message is displayed when decimal values are given in amount field | C11: 1. Login to CCC web UI 2. Create a managed opportunity >> click submit 3. On paymnet unit page, enter org pay as decimal 4. click save | D11: - User should not be able to save the payment unit - User should see the following error message: "Please enter a valid value. Nearest values are"
A12: Opp_create_11 | B12: Verify valid error message is displayed when long int values are entered | C12: 1. Login to CCC web UI 2. Create a managed opportunity >> click submit 3. On paymnet unit page, enter org pay as Long int 4. click save | D12: - User should not be able to save the payment unit - User should see the following error message: "Ensure this value is less than or equal to 2147483647".
A13: Opp_create_12 | B13: Verify valid error message is displayed when negative values are entered | C13: 1. Login to CCC web UI 2. Create a managed opportunity >> click submit 3. On paymnet unit page, enter org pay as negative values 4. click save | D13: - User should not be able to save the payment unit - User should see the following error message: "Value must be greater than or equal to 0".
A14: Opp_create_13 | B14: Verify user can't enter the special characters in the field | C14: 1. Login to CCC web UI 2. Create a managed opportunity >> click submit 3. On paymnet unit page, enter org pay as special characters | D14: - User should not be able to enter any special characters in org pay field
A15: Opp_create_14 | B15: Verify total opportunity budget reflects the sum of Org Pay across all payment units. | C15: 1. Login as PM user 2. Create opportunity with multiple payment units 3. Enter Org Pay for each payment unit 4. Save opportunity 5. Navigate to opportunity dashboard and check total budget | D15: - Total budget should get update properly
A16: Opp_create_15 | B16: Verify recalculation happens correctly when Org Pay is updated | C16: 1. Open an existing opportunity with multiple payment units 2. Edit Org Pay for one payment unit 3. Save changes 4.Refresh page/dashboard and check total budget | D16: Total opportunity budget is updated correctly based on new Org Pay
... A29: Opp_create_28 | B29: Verify user is able to create the opportunity successfully | C29: 1. Logn to CCC web UI as PM user 2. Navigate to opp list page 3. Navigate to program list page 4. Under a program click on view status >> Under NM user details click on create opportunity button 5. Create an opportunity | D29: -User should be able to create the opportunity successfully and able to land on the opportunity dashboard of the newly created opportunity

Sheet Opportunity List page
A1: Test Case ID | B1: Description | C1: Steps | D1: Outcome | E1: Status (Pass/Fail) | F1: QA Ticket | G1: Comments
A2: OLP_01 | B2: Confirm user lands on the Opportunity list page on successful login | C2: 1. Login to the CCC web UI using correct username and password https://connect-staging.dimagi.com/accounts/login | D2: - User should land on the opportunity list page and see all the programs user's been invited to - The order of the list should be such that the newest invitation be at top - Opportunities should be listed in the order of start date | E2: Pass | G2: Automated: test_olp_list_page (verify_loaded)
A3: OLP_02 | B3: Confirm user is not able to create an opportunity as NM user | D3: -User is not able to create an opportunity as NM user | E3: Pass | G3: Automated: test_olp_list_page NM (managed opportunity-init returns 403 for NM; uses seeded program_id)
A4: OLP_04 | B4: User should be able to land on the Opportunity list page when they select the option from the right pane | C4: 1. Log in to CCC web UI 2. Click on the hamburger option present on left side 3. Select the opportunities option | D4: - User should land on the opportunity list page and should see all the opportunities created by the user - If there are no opportunities created, user should see an empty list and "Create Opportunity" option on the page - User should also see "Add New" button | E4: Pass | G4: Automated: test_olp_list_page (landing)
A5: OLP_05 | B5: User should see the following information for any opportunity on the page when login with network manager - Test or Real - Status - Program Name - Start & End Date - Pending Invites - Inactive connect workers - Pending Approvals - Payment Due | C5: 1. Log in to CCC web UI 2. Navigate to opportunity list page | D5: - The columns should be displayed and give off the following info: i) Status: Active, Inactive or Ended (past end date) ii) Pending Invites: Invitations sent successfully to workers and not accepted yet iii) Inactive workers: No form submission in 3 days in Learn or Deliver app iv) Deliveries pending approval v) Payments due to workers - The Opportunities should be listed in the following order of sequence: Active on top Earliest Start Date Earliest End Date - User should be able to sort the list by clicking on any column header | E5: Pass | G5: Automated: test_olp_list_page (PM+NM columns, sortable headers)
B6: User should see the following information for any opportunity on the page when login with program manager - Test or Real - Status - Program Name - Start & End Date - Active connect workers - Total deliveries - Verified deliveries - Worker Earnings | C6: 1. Log in to CCC web UI 2. Navigate to opportunity list page | D6: - The columns should be displayed and give off the following info: i) Status: Active, Inactive or Ended (past end date) ii) Active workers iii) Count of total deliveries iv) Count of verified deliveries v) Deliveries pending approval vi) Payment amount earned by workers - The Opportunities should be listed in the following order of sequence: Active on top Earliest Start Date Earliest End Date - User should be able to sort the list by clicking on any column header
A7: OLP_06 | B7: Confirm user can filter the opportunities on the basis of Status | C7: 1. Login to CCC web UI 2. Navigate to opportunity list page 3. Click on the filter icon 4. Apply neccessary filters and click Apply | D7: User should be able to filter the opportunities on the basis of Status by selecting from the Opportunity and Status dropdown - Opportunity Dropdown All Test Live - Status Dropdown All Inactive Active Ended | E7: Pass | G7: Automated: test_olp_list_behaviour (status filter)
A8: OLP_07 | B8: Confirm user is able to navigate to different pages using the pagination | C8: 1. Login to CCC web UI 2. Navigate to opportunity list page 3. Select the rows per page 4. Navigate through the pages | D8: - The opportunity list page should only list the number of opportunities selected by the user for "Rows per page" - User should be able to navigate forward backwards using the pagination arrows | E8: Pass | G8: Automated: test_olp_list_behaviour (pagination; skips when <=20 opps)
A9: OLP_08 | B9: Confirm users can land on the opportunity page, if they select any opportunity from the list | C9: 1. Login to CCC web UI 2. Navigate to opportunity list page 3. Click on any opportunity | E9: Pass | G9: Automated: test_olp_list_page (open_opportunity)
A10: OLP_09 | B10: Verify Filters pop up modal is displayed by clicking on the filters icon on opp list page | C10: 1. Login to CCC web UI 2. Navigate to opportunity list page 3. Click on the filters icon | D10: Filters pop up modal should be displayed containing following fileds: - Is test - Status - Program (Visible only to PM users) | E10: Pass | G10: Automated: test_olp_list_page (filter modal fields)
A11: OLP_10 | B11: Verify "Is test" field drop down contains: - Yes - No | C11: 1. Login to CCC web UI 2. Navigate to opportunity list page 3. Click on the filters icon 4. Click on "Is Test" field | D11: - Test opportunities should be displayed when 'yes' is selected - Non test opportunities should be displayed when 'no' is selected | E11: Pass | G11: Automated: test_olp_list_page (is_test options)
A12: OLP_11 | B12: Verify "Status" field drop down contains: - Active - Ended - Inactive | C12: 1. Login to CCC web UI 2. Navigate to opportunity list page 3. Click on the filters icon 4. Click on "Status" field | D12: - Active opportunities should be displayed when active is selected - Ended opportunities should be displayed when ended is selected - Inactive opportunities should be displayed when inactive is selected | E12: Pass | G12: Automated: test_olp_list_page (status options)
A13: OLP_12 | B13: Verify "Program" field drop down contains list of all programs [PM user] | C13: 1. Login to CCC web UI 2. Navigate to opportunity list page 3. Click on the filters icon 4. Click on "Program" field | D13: - Verify the drop down should contain the list of all programs - Opportunities that are part of selected program should be displayed | E13: Pass | G13: Automated: test_olp_list_page (program options, PM)
A14: OLP_13 | B14: Verify on the clicking on apply button, filters are applied | C14: 1. Login to CCC web UI 2. Navigate to opportunity list page 3. Click on the filters icon 4. Apply few filters and click Apply | D14: - Selected filters should be applied on opportunities - Number of filters selected should be displayed on the filters icon | E14: Pass | G14: Automated: test_olp_list_behaviour (apply + filter badge)
A15: OLP_14 | B15: Verify user is able to select multiple options in status fileld | C15: 1. Login to CCC web UI 2. Navigate to opportunity list page 3. Click on the filters icon 4. Click on "Status field" 5. Select multiple options under status filed 6. Click on Apply | D15: - Multiple filters selected should be applied on the opportunities | E15: Pass | G15: Automated: test_olp_list_behaviour (multi-select status)
A16: OLP_15 | B16: Verify user is able to select multiple options in programs filed[PM user] | C16: 1. Login to CCC web UI 2. Navigate to opportunity list page 3. Click on the filters icon 4. Click on programs field 5. Select multiple programs under programs filed 6. Click on Apply | D16: - Opportunities related to the selected programs should be displayed | E16: Pass | G16: Automated: test_olp_list_behaviour (program filter)
A17: OLP_16 | B17: Verify Navigating away and back to a page should preserve the filters applied on the page | C17: 1. Login to CCC web UI 2. Navigate to opportunity list page 3. Apply filters 4. Navigate away and back by using arrow | D17: - Applied filters should be preserved when user navigate away and back | E17: Pass | G17: Automated: test_olp_list_behaviour (filter persistence)
A18: OLP_17 | B18: Verify user is able to see the following buttons by clicking on the three dots at the end of opportunity details - "view opportunites" - "view connect workers" - View Invoices | C18: 1. Login to CCC web UI 2. Navigate to opp list page 3. Click on the 3 dots option present at the end of opportunity details | D18: - User should be able to see the following details: View opportunites View connect workers View Invoices | E18: Pass | G18: Automated: test_olp_list_page (kebab_options)
A19: OLP_18 | B19: Verify user is able to land on the opportunity dashboard by clicking on the "view opportunity" button | C19: Cont to above TC - Click on view opportunities option | D19: - User should be land on opportunity dashboard | E19: Pass | G19: Automated: test_olp_list_behaviour (kebab View Opportunity target)
A20: OLP_19 | B20: Verify user is able to land on the connect workers by cliicking on the "view connect workers" button | C20: Cont to OLP_20 - Click on view connect workers option | D20: - User should be land on Connect workers page | E20: Pass | G20: Automated: test_olp_list_behaviour (kebab View Connect Workers target)
A21: OLP_20 | B21: Verify user is able to land on the invoices page by cliicking on the "view invoices" button | C21: Cont to OLP_20 - Click on view invoices option | D21: - User should be land on invoices page | E21: Pass | G21: Automated: test_olp_list_behaviour (kebab View Invoices target)
... A29: OLP_30 | B29: Verify when user click on the amount under "Worker Earnings" column, user should land on the payment tab [PM user] | C29: 1. Login to CCC web UI 2. Navigate to opportunity list page 3. Click on the count under "Worker Earnings" column | D29: - User should be able to land on the payments tab | E29: Pass | G29: Automated: test_olp_list_behaviour (Worker Earnings drill-down)

Sheet Opportunity dashboard
A1: Test Case ID | B1: Description | C1: Steps | D1: Outcome | E1: Status (Pass/Fail) | F1: QA Ticket | G1: Comments
A2: OD_1 | B2: Confirm user lands on the opportunity dashboard page when they select any opportunity | C2: 1. Login to CCC web UI 2. Navigate to opportunity list page 3. Click on any opportunity | D2: - User should land on the opportunity dashboard
A3: OD_2 | B3: Confirm user can see the opportunity details on the dashboard page | D3: User should be able to all the necessary correct information - Start & End Date - Total Workers invited - Count of inactive workers in the past 3 days - Total Deliveries - View progress map - Tasks assigned to connect workers - Audit opportunity - Total payment earned and due User should also be able to see the progress funnel and delivery progress graphs
A4: OD_3 | B4: Confirm user can analyse how many workers were actually invited and continuing to deliver | C4: 1. Login to CCC web UI 2.Go to opportunity list page 3. Select any opportunity 4. Navigate to opportunity dashboard 5. Verify count for connnect workers - invited, Inactive, tasks assigned to workers | D4: User should see following information under workers section - Connect workers button: User should land on connect workers page upon clicking on connect workers button - Inactive last 3 days - Tasks assigned to connect workers
A5: OD_4 | B5: Verify user see the all the information related to the deliveries under "Service Deliveries" section | C5: 1. Login to CCC web UI 2.Go to opportunity list page 3. Select any opportunity 4. Navigate to opportunity dashboard 5. Click on "services deliverd" button 6. You will land on the delivery tab | D5: Following information should be getting displayed under Deliveries section in boxes and progress bars: - Status - Name - Last delivery timestamp that updates dynamically - Delivery progress - Payment unit - Delivered - Approved - Rejected
A6: OD_5 | B6: Verify user can see all the payment related information under "Payments to Workers" section | C6: 1. Login to CCC web UI 2.Go to opportunity list page 3. Select any opportunity 4. Navigate to opportunity dashboard 5. Click on "payments earned" button 6. You will land on the payments tab | D6: Following information should be displayed under payments section in boxes and progress: - Last Payment date - Total Budget (should match top panel number) - Worker Earned amount - Worker Payments due Following details should be shown under payments tab: - Status - Name - Last active - Accrued - Total Paid - Last Paid - Confirm
A7: OD_6 | B7: Confirm user can click on the hamburger option on the opportunity dashboard page and see different options | C7: 1. Login to CCC web UI 2.Go to opportunity list page 3. Select any opportunity 4. Navigate to opportunity dashboard 5. Click on the hamburger option | D7: User should see the following options when they click on the hamburger option - Edit opportunity - Add payment unit - View Invoices - Catchment Areas - Add Workers - Add Worker Budget - Verification Flags - Send Message - Configure task types
A8: OD_7 | B8: Confirm user is taken to the verification flag on selecting "Verification Flags" option | C8: Continue from above TC - Select verification flags from hamburger option | D8: - User should see the verification flags page, when they select "Verification Flags" option - Program Manager should see all the verification flags and should be able to edit/configure them Following verification rules are shown: - Start and end time of vists submission - Minium time should be taken to submit a visit - Form validation rules If submitted visit doesn't satisfy the above verification rules, automatically visit should get rejected
A9: OD_8 | B9: Confirm user is able to send message using send message option | C9: 1. Login to CCC web Ui 2. Go to opp dahsboard 3.Click on hamburger option >> send message 4. Select the users you want to send message 5. Enter the message >> Click confirm | D9: - User should be able to send message to send message - User should recieve push notification in mobile - User should see a message sent in notification history | G9: AUTOMATION: Web part automated (Send Message page reachable) - PR #38, tests/test_opd_budget.py::test_opd_08_send_message_page. MOBILE HALF NOT AUTOMATED (push notification on device + notification history) - out of web/Playwright scope; needs a Maestro mobile hybrid test (device signs in as the enrolled worker after the web send, like TASKING_HYBRID / test_e2e_relearn_lifecycle). Prereqs: enrolled mobile worker on the opp, BrowserStack/Appium, a new Maestro flow; runs @on_demand.
A10: OD_9 | B10: Confirm user is redirected to Add Workers page when they click on the Add Workers option | C10: Two ways to add connect workers: 1. Navigate to opp dashboard Click on hamburger options Select Add connect workers option 2.On opp dashboard, select connect workers button Select "+" on connect workers tab | D10: - User should be redirected to a new page where they should see an input field and add workers to the opportunity | G10: AUTOMATION: Automated - PR #38, test_opd_budget.py::test_opd_09_add_connect_workers_redirect (redirects to user_invite; #id_users present).
A11: OD_10 | B11: Verify user is able to add budget for existing workers using add budget option | C11: 1. Login to CCC web UI 2. Navigate to Opp dashboard >> Hamburger option 3. Click on Add budget 4. Under existing workers tab, select the workers you want to add the budget 5. Enter the no.of visits and select to increase or decerase the visits 6. Extend the opportunity date if you want | D11: - User should be able to add the budget and visits for exisiting workers | G11: AUTOMATION: Automated - PR #38, test_opd_budget_mutations.py::test_opd_10 (increase visits; Max Visits reflects; mutate-then-revert on the dedicated staging Add Budget opp; net-zero).
A12: OD_11 | B12: Verify user is able to increase the visits for existing workers | C12: 1. Login to CCC web UI 2. Navigate to Opp dashboard >> Hamburger option 3. Click on Add budget 4. Under existing workers tab, select the workers you want to increase the visits 5. Enter the no.of visits and select "increase" option 6. Click save | D12: The user’s total max visits should increase proportionally across all payment units (i.e., change × number of payment units). | G12: AUTOMATION: Automated - PR #38, test_opd_budget_mutations.py::test_opd_11_increase_visits_proportional (delta = N x payment units; net-zero).
A13: OD_12 | B13: Verify user is able to increase the visits for existing workers | C13: 1. Login to CCC web UI 2. Navigate to Opp dashboard >> Hamburger option 3. Click on Add budget 4. Under existing workers tab, select the workers you want to decrease the visits 5. Enter the no.of visits and select to "decerase" option 6. Click save | D13: The user’s total max visits should decrease proportionally across all payment units (i.e., change × number of payment units). | G13: AUTOMATION: Automated - PR #38, test_opd_budget_mutations.py::test_opd_12_decrease_visits_proportional (net-zero increase-then-decrease).
A14: OD_13 | B14: Verify error pop up is displayed by entering negative numbers in the visits field | C14: 1. Login to CCC web UI 2. Navigate to Opp dashboard >> Hamburger option 3. Click on Add bduget option 4. Enter the negative number in visits field 5. Click Save | D14: - The following error message is displayed "Value must be greater than or equal to 1" | G14: AUTOMATION: Automated - PR #38, test_opd_budget.py::test_opd_13_negative_visits_validation (number_of_visits min=1 via browser ValidityState).
A15: OD_14 | B15: Confirm user is not able decrease the completed visits | C15: 1. Login to CCC web UI 2. Navigate to Opp dashboard >> Hamburger menu >> Add budget 3. Enter the number of visits including the completed count >> Click save | D15: - User should be not able to decrease the completed visits and following error message is displayed: "Cannot decrease the number of visits for user(s). The visit count cannot be reduced below the number of already completed visits or zero" | G15: AUTOMATION: Automated - PR #38, test_opd_budget_mutations.py::test_opd_14 (decrease below completed/zero rejected with 'Cannot decrease...' error; no change). Exercised via a below-zero decrease (same validation/message); the exact below-COMPLETED path additionally needs a worker with completed visits.
A16: OD_15 | B16: Verify that changes to delivery visits are correctly reflected on the Connect Workers page and on mobile. | C16: 1. Login to CCC web Ui 2. Hamuburger option >> Add budget 3. Add visits and budget to the worker >> save | D16: - Applied visit changes are updated on the connect workers page | G16: AUTOMATION: Web reflection automated (Connect Workers/Deliver max-visit denominators) - PR #38, test_opd_budget_mutations.py::test_opd_15_change_reflected_on_connect_workers. MOBILE REFLECTION NOT AUTOMATED (updated visit count on the device) - out of web scope; needs the same Maestro mobile hybrid follow-up as OD_8.
A17: OD_16 | B17: Verify that the pop-up modal displays the correct amount and number of visits based on user changes. | C17: 1. Login to CCC web Ui 2. Hamuburger option >> Add budget 3. Add visits and budget to the worker >> save 4. Pop up modal is displayed >> click confirm | D17: - Pop up modal displays the correct amount and no.of visits based on user changes | G17: AUTOMATION: Automated - PR #38, test_opd_budget.py::test_opd_16_confirm_modal_shows_computed_visits (totalVisits shown in the confirm modal; no submit).
A18: OD_17 | B18: Verify user is able to add budget for new connect workers using add budget option | C18: 1. Login to CCC web UI 2. Navigate to opp dashboard >> hamburger menu >> Add budget 3. On add budget page, select new connect workers tab 4. Enter the no.of connect workers, you want to add 5. Click save | D18: - Total budget should get auto updated upon entering the no.of connect workers - User should be able to add budget for new connect workers | G18: AUTOMATION: Automated - PR #38, test_opd_budget.py::test_opd_17_new_workers_autocalc_total_budget (total_budget auto-updates with the new-worker count).
A19: OD_18 | B19: Verify user can view the learn & deliver apps information on the dashboard | C19: 1. Login to CCC web UI 2. Navigate to opp dashboard | D19: - On clicking the Learn Apps option on the opportunity user should see a pop up dialog box with the Learn App name and the modules being used with description and estimated time to complete the learning - On the same dialog box user should see Delivery App and Payment units tab as well - Under Delivery App tab, user should see the delivery app name and all the delivery units with the delivery unit IDs - The dialog box should be non-editable
A20: OD_19 | B20: Verify user can see all the payments units information on the opportunity dashboard | C20: 1. Login to CCC web UI 2. Navigate to opp dashboard | D20: On clicking the payment units option, under Payment Units tab, user should see all the payments units with the following details - Name - Start & End Date - Amount - Total Deliveries - Max Daily - Delivery Units
A21: OD_18 | B21: Verify user pre filters are applied when we click on the following buttons: - Inactive workers | C21: 1. Login to CCC web UI 2. Navigate to opp dashboard 3. Click on the "Inactive workers" button | D21: - User should be able to land on workers delivery page - Inactive filters should be pre applied
A22: OD_20 | B22: Confirm the hamburger menu differs by role (PM vs Network Manager) | C22: 1. Login as a Program Manager (PM_Automation_01) 2. Open an opportunity dashboard 3. Open the hamburger menu and note options 4. Repeat as a Network Manager on the same opportunity | D22: PM sees the full set incl. Edit Opportunity, Add Payment Unit, Verification Rules, Configure Task Types. Network Manager sees only the non-PM subset (View Invoices, Catchment Areas, Add Budget, Send Message, and Add Connect Workers when not ended). | G22: Added from source-derived gap analysis (2026-08-26), beyond documented OD_1-OD_19. Src: opportunity_menu.html:13-65 (is_opportunity_pm gating). | AUTOMATION: Automated - PR #38, test_opd_gaps.py::test_opd_20 (NM view of the manual opp via nm_automation; PM-only menu items absent).
A23: OD_21 | B23: Confirm a Viewer has read-only access to the dashboard | C23: 1. Login as a user with the VIEWER org role 2. Open an opportunity dashboard 3. Try to open the hamburger menu 4. Inspect worker-tab action buttons | D23: Dashboard and all stat panels load for the viewer. The hamburger icon is non-interactive (menu cannot be opened). Action controls (Add Worker, Resend Invite, Delete, Exports/Imports) are disabled. | G23: Added from source-derived gap analysis (2026-08-26), beyond documented OD_1-OD_19. Src: dashboard.html:33-40 (viewer icon has no @click); workers.html action gating. | AUTOMATION: Automated - PR #38, test_opd_gaps.py::test_opd_21 (VIEWER via direct Connect login - email/password, no HQ; loads a dashboard but cannot open the hamburger menu). Viewer creds in gitignored settings.cfg [viewer]; skips if absent.
A24: OD_22 | B24: Confirm a standalone (non-program-managed) opportunity hides PM-only menu items | C24: 1. Open a standalone opportunity (not owned by a program-manager org) 2. Open the hamburger menu | D24: PM-only items (Edit Opportunity, Add Payment Unit, Verification Rules, Configure Task Types) are not shown because is_opportunity_pm is False for standalone opps. | G24: Added from source-derived gap analysis (2026-08-26), beyond documented OD_1-OD_19. Src: program/utils.py:5-19; users/middleware.py:36-52. | AUTOMATION: DEPRECATED - no standalone (non-program) opps exist; migrated to legacy program (Anshu 2026-09-04, pending Nitin confirm). Test skips.
A25: OD_23 | B25: Confirm an opportunity with incomplete setup redirects to Add Payment Units | C25: 1. Open an opportunity whose setup is not complete (no payment units) 2. Navigate to its dashboard URL | D25: Instead of the dashboard, the user is redirected to the Add Payment Units page with a warning message. | G25: Added from source-derived gap analysis (2026-08-26), beyond documented OD_1-OD_19. Src: views.py:455-459 (is_setup_complete guard). | AUTOMATION: Automated - PR #38, test_opd_gaps.py::test_opd_23 (setup-incomplete opp redirects to Add Payment Units).
A26: OD_24 | B26: Confirm the status badge is correct for Active / Ended / Inactive opportunities | C26: 1. Open an Active opportunity and read the status badge 2. Repeat for an ended opportunity (past end date) and an inactive one | D26: Badge reads Active (positive), Ended (warning) or Inactive (negative) matching the opportunity state. | F26: Potential product risk | G26: Added from source-derived gap analysis (2026-08-26), beyond documented OD_1-OD_19. NOTE: 'Ended' branch reads raw object.active while 'Active' reads is_active property - verify an ended-but-active opp badges as intended. Src: dashboard.html:94-100.
A27: OD_25 | B27: Confirm an empty opportunity (0 workers/deliveries/payments) renders without errors | C27: 1. Open a newly-created opportunity with no invited workers, deliveries or payments 2. Review all dashboard cards, progress bars and timestamps | D27: Counts render as 0, progress bars show 0% (no divide-by-zero), and 'Last Delivery'/'Last Payment' show '--'; no errors or blank panels. | G27: Added from source-derived gap analysis (2026-08-26), beyond documented OD_1-OD_19. Src: views.py:3051-3053 safe_percent; 3207-3213 fallbacks; 470-475 safe_display.
A28: OD_26 | B28: Confirm a Test opportunity (is_test) renders the Test badge and test theme | C28: 1. Open an opportunity flagged as a test opportunity 2. Observe the header badge and card styling | D28: A 'Test' badge is shown and the dashboard uses the test visual theme (distinct card colours/separators). | G28: Added from source-derived gap analysis (2026-08-26), beyond documented OD_1-OD_19. Src: dashboard.html:5,27,32,90. | AUTOMATION: Automated - PR #38, test_opd_gaps.py::test_opd_26 (Test badge on an is_test opp; OLP Test opp).
A29: OD_27 | B29: Confirm currency values are formatted correctly across the dashboard | C29: 1. Open an opportunity with a currency set 2. Compare Max Budget (basic details), the Worker Payments panel title, and the worker-progress earned/paid values | D29: All monetary values show the correct currency code and thousands separators consistently across the three surfaces. | G29: Added from source-derived gap analysis (2026-08-26), beyond documented OD_1-OD_19. Src: views.py:525, 3060-3061, 3211 (three currency-format paths).
A30: OD_28 | B30: Confirm MICROPLANNING flag controls the Work Areas tab and Progress Map | C30: 1. Open an opportunity with the MICROPLANNING flag ON: check the worker Work Areas tab and 'View Progress Map' 2. Repeat with the flag OFF, and also request the work-areas URL directly | D30: Flag ON: Work Areas tab is present and View Progress Map opens microplanning. Flag OFF: the Work Areas tab is absent and the direct work-areas URL returns 404. | G30: Added from source-derived gap analysis (2026-08-26), beyond documented OD_1-OD_19. Src: views.py:2646-2653, 2849-2852 (WorkerWorkAreaView 404). | AUTOMATION: Automated - PR #38, test_opd_gaps.py::test_opd_28 (MICROPLANNING opp: Work Area Assignments tab + work-areas URL 200; OLP Test opp).
A31: OD_29 | B31: Confirm the View Progress Map / Audit Opportunity / Tasks Assigned panels navigate correctly | C31: 1. On the dashboard, click 'View Progress Map', 'Audit Opportunity' and 'Tasks Assigned to Connect Workers' panels in turn | D31: Each opens its target page (microplanning home, audit report list, assigned task list) and enforces access control (no unhandled error/403). | F31: Potential product risk | G31: Added from source-derived gap analysis (2026-08-26), beyond documented OD_1-OD_19. NOTE: these links render on every opportunity with no MICROPLANNING guard - verify they don't 404/deny on non-microplanning opps. Src: views.py:3152-3201.
A32: OD_30 | B32: Confirm 24h increment badges appear only on Services Delivered and Payments Earned | C32: 1. Open an opportunity with deliveries/payments in the last 24h 2. Inspect each stat panel for the increment badge | D32: An increment 'up-arrow' badge (with a 'last 24 hours' tooltip) shows on the Services Delivered and Payments Earned panels only; other panels show no increment. | G32: Added from source-derived gap analysis (2026-08-26), beyond documented OD_1-OD_19. Src: opportunity_delivery_stat.html:56-62; views.py:3150, 3223. | AUTOMATION: DESCOPED (Anshu+Akanksha 2026-09-04) - the '24h increment' badge needs deliveries/payments submitted in the last 24h; no standalone web test can keep that fresh and no daily cadence exists. Proper home is inside the delivery-submitting E2E test (test_e2e_relearn_lifecycle): assert the badge right after it submits a visit. Fold in if prioritised.
A33: OD_31 | B33: Confirm the Worker Progress Funnel shows all 7 stages with correct counts and tooltips | C33: 1. Open an opportunity dashboard 2. Read each funnel stage count and hover its tooltip | D33: Seven stages render - Invited, Accepted, Started Learning, Completed Learning, Completed Assessment, Claimed Job, Started Delivery - with correct counts (Accepted = Invited - pending) and tooltips. | G33: Added from source-derived gap analysis (2026-08-26), beyond documented OD_1-OD_19. Src: views.py:2989-3037.
A34: OD_32 | B34: Confirm worker-progress bars show Approved/Rejected and Earned/Paid percentages with tooltips | C34: 1. Open an opportunity with deliveries and payments 2. Inspect the worker-progress section bars and tooltips | D34: Bars show Approved/Rejected as % of total deliveries and Earned/Paid as % of budget/accrued, each with the correct percentage, badge and tooltip. | G34: Added from source-derived gap analysis (2026-08-26), beyond documented OD_1-OD_19. Src: views.py:3055-3116.
A35: OD_33 | B35: Confirm resource cards show live counts and open the modal on the correct tab | C35: 1. On the dashboard, note the counts on the Learn App / Deliver App / Payment Units cards 2. Click each card | D35: Each card shows the live count and opens the resource modal pre-selected to the matching tab (Learn App / Deliver App / Payment Units). | G35: Added from source-derived gap analysis (2026-08-26), beyond documented OD_1-OD_19. Src: views.py:466-489; dashboard.html:58-69.
A36: OD_34 | B36: Confirm Edit Opportunity, Add Payment Unit and Configure Task Types open (PM) | C36: 1. As PM, open the hamburger menu 2. Click Edit Opportunity, then Add Payment Unit, then Configure Task Types | D36: Each option opens its respective PM configuration page. | G36: Added from source-derived gap analysis (2026-08-26), beyond documented OD_1-OD_19. Src: opportunity_menu.html:15,19,62.
A37: OD_35 | B37: Confirm View Invoices opens the invoice list for all roles | C37: 1. Open the hamburger menu (any role) 2. Click View Invoices | D37: The invoice list page opens for PM and non-PM members; PM additionally sees the invoice-ticket link. | G37: Added from source-derived gap analysis (2026-08-26), beyond documented OD_1-OD_19. Src: opportunity_menu.html:24; views.py:1789.
A38: OD_36 | B38: Confirm Catchment Areas import validates columns and export downloads a file | C38: 1. Open hamburger >> Catchment Areas >> Import; upload a file missing required columns 2. Then use Export | D38: Import rejects/validates against required columns (Area Name, Active, Latitude, Longitude, Site code, Radius); Export downloads the catchment file. | G38: Added from source-derived gap analysis (2026-08-26), beyond documented OD_1-OD_19. Src: opportunity_menu.html:27-39; dashboard.html:111-114. | AUTOMATION: Automated - PR #38, tests/test_opd_exports.py (catchment Export queues a background task; Import with missing columns rejected). Non-mutating.
A39: OD_37 | B39: Confirm Add Connect Workers is hidden when the opportunity has ended | C39: 1. Open an ended opportunity's hamburger menu | D39: The 'Add Connect Workers' option is not shown for an ended opportunity. | G39: Added from source-derived gap analysis (2026-08-26), beyond documented OD_1-OD_19. Src: opportunity_menu.html:40 (has_ended). | AUTOMATION: Automated - PR #38, test_opd_gaps.py::test_opd_37 (Add Connect Workers hidden when Ended). Self-skips until the fixture opp's end date passes.
A40: OD_38 | B40: Confirm the Learn tab shows learn columns and per-worker learn progress | C40: 1. Open the opportunity >> Connect Workers >> Learn tab | D40: The Learn tab lists workers with learn columns (Started/Completed Learning, modules completed, assessment, attempts, learning hours) and per-worker learn history. | G40: Added from source-derived gap analysis (2026-08-26), beyond documented OD_1-OD_19. Src: views.py:2590-2596; tables.py:1366.
A41: OD_39 | B41: Confirm the Tasks tab shows task columns and its filters | C41: 1. Open the opportunity >> Tasks tab 2. Apply the worker-name, task-status, task-type and date-range filters | D41: The Tasks tab lists tasks with the correct columns and each filter narrows the results as expected. | G41: Added from source-derived gap analysis (2026-08-26), beyond documented OD_1-OD_19. Src: views.py:2590-2596; filters.py:166-200; tables.py:1333.
A42: OD_40 | B42: Confirm the Connect Workers tab count and the worker search | C42: 1. Open the Connect Workers tab and note the '(N)' count in the tab label 2. Search by name/phone in the search box and use the clear button | D42: The tab label shows the live worker count; search filters the table, shows a 'Displaying X of Y' line, and the clear button restores the full list. | G42: Added from source-derived gap analysis (2026-08-26), beyond documented OD_1-OD_19. Src: views.py:2640-2641, 2707-2723; workers.html:10-33.
A43: OD_41 | B43: Confirm per-tab filters persist across tab navigation | C43: 1. Apply a filter on the Deliver tab 2. Switch to another tab and back 3. Then re-enter the workers area from elsewhere | D43: The applied filter is retained per tab while navigating between tabs, and is cleared when the workers area is entered from an external page. | G43: Added from source-derived gap analysis (2026-08-26), beyond documented OD_1-OD_19. Src: views.py:2598-2637 (session/referer-based filter persistence).
... A46: OD_44 | B46: Confirm the Deliver tab export offers NM vs PM sheets and completes the download flow | C46: 1. On the Deliver tab, open the export modal 2. Choose 'User Visits Sheet' (NM) then 'PM Review Sheet' (PM) and export 3. Follow the export-status spinner to download | D46: The radio switches between the NM Visits Sheet and PM Review Sheet exports; the export queues, the status banner shows progress, and the file downloads. PM-review options are hidden when auto-verification is on. | G46: Added from source-derived gap analysis (2026-08-26), beyond documented OD_1-OD_19. | AUTOMATION: Automated - PR #38, tests/test_opd_exports.py::test_opd_44_deliver_export_flow. Runs on the manual-verification opp 'Manual approval opp' (org pm_automation_02, staging) and asserts BOTH the NM 'User Visits Sheet' and PM 'PM Review Sheet' export options; the background export queue is best-effort (required-heavy HTMX form). Staging only (manual-flow opp does not exist on prod).
A47: OD_45 | B47: Confirm export/download enforces opportunity ownership (security) | C47: 1. Start an export in opportunity A to obtain an export_task_id 2. Request export_status/download_export for opportunity B using A's task id | D47: The cross-opportunity request is rejected (404); a user cannot download another opportunity's export via its task id. | F47: Potential product risk | G47: Added from source-derived gap analysis (2026-08-26), beyond documented OD_1-OD_19. Src: views.py:536-602 (get_opportunity_or_404 on the task args).
A48: OD_46 | B48: Confirm visit and payment imports validate file type and columns | C48: 1. On the Deliver tab, import a non-csv/xlsx file 2. On the Payments tab, import a file missing the required columns | D48: Non-csv/xlsx uploads are rejected; the payment import requires Username/Amount/Payment Date columns and reports errors otherwise. Import titles differ ('Import PM Review Sheet' vs 'Import Verified Visits'). | G48: Added from source-derived gap analysis (2026-08-26), beyond documented OD_1-OD_19. | AUTOMATION: Automated - PR #38, tests/test_opd_exports.py. Payments import rejects non-csv/xlsx ('File format not supported'). Visit-status import runs on the manual-verification opp (pm_automation_02, staging) and rejects a non-csv/xlsx file. Staging only for the visit import (hidden under auto-verification).
A49: OD_47 | B49: Confirm the dashboard stat HTMX endpoints load independently and are viewer-accessible | C49: 1. Load the dashboard and observe delivery_stats, worker_progress_stats and funnel_progress_stats loading 2. Request each endpoint directly, including as a viewer | D49: Each stat section loads via its own HTMX request on page load and each endpoint responds successfully, including for the VIEWER role. | G49: Added from source-derived gap analysis (2026-08-26), beyond documented OD_1-OD_19. Src: urls.py:164-173; @org_viewer_required.

Sheet Connect workers page
A1: Test Case ID | B1: Description | C1: Steps | D1: Outcome | E1: Status (Pass/Fail) | F1: QA Ticket | G1: Comments
B2: Module: Connect Workers tab
A3: Connect_worker_01 | B3: Confirm user is redirected to the Worker's List page on clicking click on ‘Connect Workers’ | C3: 1. Login to CCC web UI 2. Navigate to opp dashboard 3. Click on "connect workers" button | D3: User should be redirected to the list of workers with all the information/details of the workers - Status - Worker Name with ConnectID to distinguish 2 workers with the same name - Phone number - Invited date - Last Active in days and hours is the last time of form submission in the Learn OR Delivery app depending on whether Delivery has started - Started Learn timestamp - Completed Learn timestamp - Time to complete Learning - First Delivery timestamp - Time to start Delivery | G3: ✅ Automated (Playwright, feature/workers-web-automation): test_worker_list_view.py::test_wlv_01_02_03 (migration)
B4: Verify user is able to search connect worker using search button | C4: 1. Login to CCC web UI 2. Navigate to opp dashboard 3. Click on "connect workers" button | D4: - Enter worker name or phone number in search field, automatic search process will apply
A5: Connect_worker_02 | B5: verify user is able to see the status as invite pending until the invitation is accepted | D5: -The worker's status should be displayed as "Invite Pending" when hovering over the icon. | G5: ✅ Automated (Playwright, feature/workers-web-automation): test_worker_invites.py::test_connect_worker_02_pending_invite_status
A6: Connect_worker_03 | B6: Verify resend/delete invite buttons are enable only when user select the invites | C6: 1. Login to CCC web UI 2. Navigate to opp dashboard 3. Click on "connect workers" button 4. Select the connect users | D6: - Resend invite icon [rounded arrow] and delete invites button should be enable only when users are selected | G6: ✅ Automated (Playwright, feature/workers-web-automation): test_worker_invites.py::test_connect_worker_03_resend_delete_gated_by_selection
A7: Connect_worker_04 | B7: Verify worker status is updated to "invite accepted" when the invitation for an opportunity is accepted | D7: - When worker accepts the invitation by clicking on link status should get updated to "invite accepted" | G7: ✅ Automated (Playwright, feature/workers-web-automation): test_worker_lifecycle.py::test_connect_worker_04_accepted_status (Worker_Lifecycle_Automation)
A8: Connect_worker_05 | B8: Verify we are able to pre invite the worker[Not registered for personal ID yet] | C8: 1. Login to CCC web UI 2. Navigate to opp dashboard 3. Click on "connect workers" button 4. Click on "+Add worker" button 5. Invite user which don't have PID | D8: - User should able to invite the worker who is not yet registered for personal ID - Status should be displayed as "user not found" | G8: ✅ Automated (Playwright, feature/workers-web-automation): test_worker_invites.py::test_connect_worker_05_12_08_invite_resend_delete
A9: Connect_worker_06 | B9: Verify mobile number is displayed for "not found users" under name column | C9: 1. Login to CCC web UI 2. Navigate to opp dashboard 3. Click on "connect workers" button 4. Click on "+Add worker" button 5. Invite user which don't have PID 6. Mobile number is displayed for such users | D9: - User should see the mobile number for not found users under Name column. | G9: ✅ Automated (Playwright): test_worker_lifecycle.py::test_connect_worker_06_not_found_display (seeded not-found +74261291230, status "User not found", "—" under Name).
A10: Connect_worker_07 | B10: verify status is updated to "user suspended" when worker is suspended | C10: 1. Login to CCC web UI 2. Navigate to worker visits verification page 3. Click on the woker name 4. Select suspend button on user details pop up | D10: - user should be suspended from the opportunity - Status should get updated to user suspended | G10: ✅ Automated (Playwright, feature/workers-web-automation): test_worker_lifecycle.py::test_connect_worker_07_suspended_status (+ suspend/revoke action in test_worker_visit_verification.py)
A11: Connect_worker_08 | B11: verify user is able to delete the pending invites | C11: 1. Login to CCC web UI 2. Navigate to opp dashboard 3. Click on "connect workers" button 4. Select the connect users 5. Click on delete icon | D11: - selected pending invites should be deleted - User should delete pending invites as a bulk or an individual | G11: ✅ Automated (Playwright, feature/workers-web-automation): test_worker_invites.py::test_connect_worker_05_12_08_invite_resend_delete
A12: Connect_worker_09 | B12: Verify user is not able to resend the invite for pending users within 24 hrs[Cooldown period] | C12: 1. Login to CCC web UI 2. Navigate to opp dashboard 3. Click on "connect workers" button 4. Select the connect users 5. Click on resend invite icon | D12: - "The following invites were skipped, as they were sent in the last 24 hours" message should be displayed | G12: 🔴 Manual only (by design) (decided 2026-10-02): the cooldown only exists for a real registered number and every invite/resend texts it, so it cannot be refreshed on each CI run without texting a real person (demo numbers send no SMS, so they never enforce the cooldown). No automated test; QA runs it by hand before releases.
A13: Connect_worker_10 | B13: Verify user is able to resend the invite for "invite pending" worker successfully after 24 hrs | C13: 1. Login to CCC web UI 2. Navigate to opp dashboard 3. Click on "connect workers" button 4. Select the connect users[invite pending users] 5. Click on resend invite icon | D13: - "Successfully invites send" message should be displayed including the number of skipped and resend invites | G13: ✅ Automated (Playwright, feature/workers-web-automation): test_worker_lifecycle.py::test_connect_worker_10_resend_allowed_for_pending
A14: Connect_worker_11 | B14: verify user is not able to resend/delete the invite for accepted workers | C14: 1. Login to CCC web UI 2. Navigate to opp dashboard 3. Click on "connect workers" button 4. Select the connect users[accepted user] 5. Click on resend invite icon | D14: - "Cannot delete invite(s). Accepted invites cannot be deleted" message should be displayed - "The following invites were skipped, as they have already accepted" message should be displayed | G14: ✅ Automated (Playwright, feature/workers-web-automation): test_worker_lifecycle.py::test_connect_worker_11_resend_skipped_for_accepted
A15: Connect_worker_12 | B15: verify user is not able to resend invite for not found users | C15: 1. Login to CCC web UI 2. Navigate to opp dashboard 3. Click on "connect workers" button 4. Select the connect users[not found user] 5. Click on resend invite icon | D15: - "The following invites were skipped, as they are not registered on PersonalID" message should be displayed | G15: ✅ Automated (Playwright, feature/workers-web-automation): test_worker_invites.py::test_connect_worker_05_12_08_invite_resend_delete
A16: Connect_worker_13 | B16: verify user is able to delete not found users | C16: 1. Login to CCC web UI 2. Navigate to opp dashboard 3. Click on "connect workers" button 4. Select the connect users [not found user] 5. Click on delete icon | D16: - User should be able to delete the selected user as a bulk or an individual | G16: ✅ Automated (Playwright): test_worker_lifecycle.py::test_connect_worker_13_not_found_deletable (Delete affordance on the seeded not-found user; not executed to preserve the seed).
A17: Connect_worker_14 | B17: verify user is not able to resend/delete invite for suspend user | C17: 1. Login to CCC web UI 2. Navigate to opp dashboard 3. Click on "connect workers" button 4. Select the connect users[Suspended user] 5. Click on delete icon | D17: - "Cannot delete invite(s). Accepted invites cannot be deleted" message should be displayed - "The following invites were skipped, as they have already accepted" message should be displayed | G17: ✅ Automated (Playwright, feature/workers-web-automation): test_worker_lifecycle.py::test_connect_worker_14_resend_skipped_for_suspended
A18: Connect_worker_15 | B18: verify appropriate messages are displayed when user sends invite to all types of users as a bulk [accepted,suspended,pending,not found] | C18: 1. Login to CCC web UI 2. Navigate to opp dashboard 3. Click on "connect workers" button 4. Select the connect users 5. Click on resend invite icon | D18: - The following messages are displayed: Accepted/Suspended user: "The following invites were skipped, as they have already accepted" Not found user: "The following invites were skipped, as they are not registered on PersonalID" Pending user: "Successfully sent invites" [after 24 hrs] "The following invites were skipped, as they were sent in the last 24 hours" [within 24 hrs] | G18: ✅ Automated (Playwright, feature/workers-web-automation): test_worker_lifecycle.py::test_connect_worker_15_bulk_resend_messages
A19: Connect_worker_16 | B19: verify appropriate messages are displayed when user delete invites of all types of users [accepted,suspended,pending,not found] as bulk | C19: 1. Login to CCC web UI 2. Navigate to opp dashboard 3. Click on "connect workers" button 4. Select the connect users 5. Click on delete icon | D19: - The following messages are displayed: Accepted/Suspended user: "Cannot delete invite(s). Accepted invites cannot be deleted" pending/not found user: "Successfully deleted invites" | G19: ⏸ Deferred - bulk delete across all types would delete the seeded pending/accepted workers (destructive). Not automated to protect the seed.
A20: Connect_worker_17 | B20: Verify user can sort the workers list by clicking the header columns | C20: 1. Login to CCC web UI 2. Navigate to opp dashboard 3. Click on "connect workers" button 4. User redirects to workers list page 5. Sort the workers list by clicking on sort arrows | D20: - By default, list should be in the order of recency of the ‘last active worker’ column with the most recent activity listed on top - User should be able to flip the list by clicking on the ‘Last Activity’ column head - When clicking any of the column head with dates are clicked, the list should get sorted by the most recent date of that column and reversed when clicked again - When the worker name column head is clicked, the list is order alphabetically by worker name - When the ‘days to start delivery’ column head is clicked, the rows are ordered in descending order of the value of the column | G20: ✅ Automated (Playwright, feature/workers-web-automation): test_worker_list_view.py::test_connect_worker_17_sort_list_by_header
B21: Module: Learn tab
A22: Learn_tab_01 | B22: Verify user can click on the Learn Tab, on the workers list page and see all the workers learn progress | C22: 1. Login to CCC web UI 2. Navigate to opp dashboard 3. Click on "connect workers" button 4. Select learn tab | D22: User should more detailed information about user's learning progress such as - Last Active represents the last form submission of Learn or Deliver app - Modules Completed, this should show the learn progress percentage - Assessment completed or not - Attempts taken to complete the assessment - Learning hours represents the total spent time learning that adds up the time spent learning each module through multiple passes up until the assessment is passed - Clicking on the forward arrow of a worker row leads to a page that lists all the modules completed and their date of completion and time spent and should show if a module is completed all times | G22: ✅ Automated (Playwright, feature/workers-web-automation): test_worker_list_view.py::test_wlv_01_02_03 (migration)
A23: Learn_tab_02 | B23: Verify modules completed progress is updated as we submit learn apps is mobile | C23: 1. Login to CCC web UI 2. Navigate to opp dashboard 3. Click on "connect workers" button 4. Select learn tab | D23: - Progress percentange should increase and should be same as of mobile as user submits the learn app | G23: 🔴 Not automated (web) - requires a mobile learn-app submission during the test; web-only cannot drive it.
A24: Learn_tab_03 | B24: Verfiy Assessment status is shown as failed when user fails the assessment in mobile | C24: 1. Login to CCC web UI 2. Navigate to opp dashboard 3. Click on "connect workers" button 4. Select learn tab | D24: - When user fails assessment in mobile when should get updated to Failed | G24: ✅ Automated (Playwright, feature/workers-web-automation): test_worker_lifecycle.py::test_learn_tab_03_assessment_failed (Map_09)
A25: Learn_tab_04 | B25: Verfiy Assessment status is shown as Passed when user pass the assessment in mobile | C25: 1. Login to CCC web UI 2. Navigate to opp dashboard 3. Click on "connect workers" button 4. Select learn tab | D25: - When user pass assessment in mobile when should get updated to Passed | G25: ✅ Automated (Playwright, feature/workers-web-automation): test_worker_list_view.py::test_learn_tab_04_assessment_passed
B26: Module: Delivery tab
A27: Delivery_tab_01 | B27: Verify user can access the delivery tab, with all the delivery information for an opportunity | C27: 1. Login to CCC web UI 2. Navigate to opp dashboard 3. Click on "connect workers" button 4. Select delivery tab | D27: User should be able to land on the delivery by clicking on Total Services Delivered on the Opportunity Dashboard when I want to explore the stats for the entire list of workers | G27: ✅ Automated (Playwright, feature/workers-web-automation): test_worker_list_view.py::test_wlv_01_02_03 (Deliver tab, migration)
A28: Delivery_tab_02 | B28: Verify user sees all the delivery details when they are on the delivery tab | C28: 1. Login to CCC web UI 2. Navigate to opp dashboard 3. Click on "connect workers" button 4. Select delivery tab | D28: User should see the followig delivery information for each user - The worker list should be ordered by the most recent activity in the ‘last active’ column. It should be possible to reverse this order by clicking on the column header - The Last Delivery column should display the timestamp of completion for that specific payment unit | G28: ✅ Automated (Playwright, feature/workers-web-automation): test_worker_list_view.py::test_wlv_01_02_03 (deliver headers)
A29: Delivery_tab_03 | B29: Ensure when user clicks on the number in the 'Delivered' column, they see a breakdown of the deliveries | C29: 1. Login to CCC web UI 2. Navigate to opp dashboard 3. Click on "connect workers" button 4. Select delivery tab 5. Click on count of visits | D29: When clicking on the number in the delivered column, user should see a breakdown of the deliveries such as - Completed - Over Limit - Incomplete | G29: ✅ Automated (Playwright, feature/workers-web-automation): test_worker_list_view.py::test_wlv_04_worker_status_count_breakdown (Delivered)
A30: Delivery_tab_05 | B30: Confirm on clicking the number in 'Approved' column, users can see the breakdown of th deliveries | C30: 1. Login to CCC web UI 2. Navigate to opp dashboard 3. Click on "connect workers" button 4. Select delivery tab 5. Click on count of visits | D30: When clicking on the number in the Approved column, user should see a breakdown of the deliveries | G30: ✅ Automated (Playwright, feature/workers-web-automation): test_worker_list_view.py::test_wlv_04/05 (Approved breakdown)
A31: Delivery_tab_06 | B31: Verify that the visit count is considered as 1 per payment unit, even if it includes multiple required or optional visits. | C31: 1. Login to CCC web UI 2. Navigate to opp dashboard 3. Click on "connect workers" button 4. Submit one form from mobile - verify count shows as 1 5. Submit another form which is configured for payment unit used in above step | D31: - Visit count should be as 1 for one payment unit even multiple required/optional visits are configured | G31: ⏸ Deferred - delivery-completion logic (1 visit per payment unit); eng-covered, needs controlled visit data.
A32: Delivery_tab_07 | B32: Verify that the delivery is marked as complete when all required visits are submitted and approved, and at least one optional visit (if present) is approved. | C32: 1. Login to CCC web UI 2. Navigate to opp dashboard 3. Click on "connect workers" button 4. Submit forms from mobile - Verify that visit is shown as pending 5. Complete all the visits(required/optional) for a particular payment unit | D32: - Visit count is marked as complete and approved from pending state once all the visits (required/optional) for one payment unit are submitted and approved | G32: ⏸ Deferred - delivery-completion rule (required + optional approved); eng-covered, needs controlled visit data.
A33: Delivery_tab_09 | B33: Confirm on clicking the number in 'Rejected' column, users can see the breakdown of th deliveries | C33: 1. Login to CCC web UI 2. Navigate to opp dashboard 3. Click on "connect workers" button 4. Select delivery tab 5. Click on count of visits | D33: When clicking on the number in the Approved column, user should see a breakdown of the deliveries: - Breakdown by flag types - Over Limit - Missing value forms - Duration - User suspended | G33: ✅ Automated (Playwright, feature/workers-web-automation): test_worker_list_view.py::test_wlv_04/05 (Rejected breakdown)
A34: Delivery_tab_10 | B34: Verify Filters pop up modal is displayed by clicking on the filters icon present in right corner on delivery tab | C34: 1. Login to CCC web UI 2. Navigate to opp dashboard 3. Click on "connect workers" button 4. Select delivery tab 5. Click on the filters icon 6. Apply the filters | D34: pop up modal should be displayed with following fields - Last Active - Has duplicate deliveries - Deliveries with flags - Has overlimit Deliveries - Deliveries with pending review - Close and Apply buttons | G34: ✅ Automated (Playwright, feature/workers-web-automation): test_worker_deliver_filters.py::test_delivery_tab_10_filter_modal_opens
A35: Delivery_tab_11 | B35: Verify last active filed dropdown contains following options: - Any time - 1 day ago - 3 days ago - 7 days ago | C35: 1. Login to CCC web UI 2. Navigate to opp dashboard 3. Click on "connect workers" button 4. Select delivery tab 3. Click on the filters icon 4. Click on "Last Active" field | D35: - When user select any time, workers that are not active anytime should be displayed - When user select 1 day ago, workers that are not active 1 day ago should be displayed - When user select 3 days ago, workers that are not active 1 or 3 days ago should be displayed. - When user select 7 days ago, workers that are not active 1 or 3 or 7 days ago should be displayed. | G35: ✅ Automated (Playwright, feature/workers-web-automation): test_worker_deliver_filters.py::test_delivery_tab_11_last_active_options
A36: Delivery_tab_13 | B36: Verify "Deliveries with flags" filed dropdown contains following options: - Yes - No | C36: 1. Login to CCC web UI 2. Navigate to opp dashboard 3. Click on "connect workers" button 4. Select delivery tab 5. Click on the filters icon 6. Click on "Deliveries with flags" field | D36: - When user select Yes, workers that submitted deliveries with flag should be displayed - When user selects No, workers that not submitted deliveries with flag should be displayed | G36: ✅ Automated (Playwright, feature/workers-web-automation): test_worker_deliver_filters.py::test_delivery_tab_13_deliveries_with_flags_options
A37: Delivery_tab_14 | B37: Verify "Has overlimit Deliveries" filed dropdown contains following options: - Yes - No | C37: 1. Login to CCC web UI 2. Navigate to opp dashboard 3. Click on "connect workers" button 4. Select delivery tab 5. Click on the filters icon 6. Click on "Has overlimit Deliveries" field | D37: - When user select Yes, workers that submitted overlimit deliveries should be displayed - When user selects No, workers that not submitted overlimit deliveries should be displayed | G37: ✅ Automated (Playwright, feature/workers-web-automation): test_worker_deliver_filters.py::test_delivery_tab_14_has_overlimit_options
A38: Delivery_tab_16 | B38: Ensure that all filter combinations are applied simultaneously and function correctly. | C38: 1. Login to CCC web UI 2. Navigate to opp dashboard 3. Click on "connect workers" button 4. Select delivery tab 5. Click on the filters icon 6. Apply all the filters | D38: - Workers should be displayed based on the selected filters | G38: ✅ Automated (Playwright, feature/workers-web-automation): test_worker_deliver_filters.py::test_delivery_tab_16_filter_combination_applies
B39: Module: Payment processing
A40: Payment Processing_1 | B40: Confirm user sees all the payment info under "Payments" tab on the Workers List page | C40: 1. Login to CCC web UI 2. Navigate to opp dashboard 3. Click on "connect workers" button 4. Select payment tab | D40: - On navigating to the payments tab on the workers list page, user should see following columns i) Worker Name and CID ii) Earnings Accrued iii) Paid Amount iv) Last Paid Date - User should be able to see the entire history of payments for a worker by clicking on a cell in the last paid column | G40: ✅ Automated (Playwright, feature/workers-web-automation): test_worker_payments.py::test_payment_processing_01_02_03_04
A41: Payment Processing_2 | B41: Confirm user sees a message when they click on the Pay button | D41: - User should see a transaction success or failed message when they hit the Pay button | G41: ✅ Automated (Playwright, feature/workers-web-automation): test_worker_payments.py (import-confirmation path)
A42: Payment Processing_3 | B42: User should be able to see the payment history by clicking the icon | C42: 1. Login to CCC web UI 2. Navigate to opp dashboard 3. Click on "connect workers" button 4. Select payment tab 5. Click on the last paid date | D42: User should be able to see the history of payments made: - Paid field should show total amount paid in that batch of payments uploaded - ‘X’ workers shows the number of workers paid - Timestamp of payment - User who uploaded the payment (nice-to-have) | G42: ✅ Automated (Playwright, feature/workers-web-automation): test_worker_payments.py (last-paid history popup)
A43: Payment Processing_4 | B43: Confirm user can rollback a payment made to the worker | C43: 1. Login to CCC web UI 2. Navigate to opp dashboard 3. Click on "connect workers" button 4. Select payment tab 5. Click on the last paid date 6. Click on rollback payment button | D43: - User should be able to rollback any payment batch by hitting a button next to the payment batch in the history - User should see success or failure message after they rollback a payment | G43: ✅ Automated (Playwright, feature/workers-web-automation): test_worker_payments.py (rollback)
A44: GAP-SRC-W-46 | B44: Worker profile KPI header: Total Visits, Pending Tasks (links to filtered tasks), Rejected Visits with per-flag rejection popup, Accrued Amount, Paid Amount with last-payment popup (only when a payment exists). Src: get_worker_kpi_context (~2125-2167) + worker_profile_kpi.html. | G44: ✅ Automated (Playwright): test_worker_gaps.py::test_src_w_46_worker_profile_kpis
A45: GAP-SRC-W-47 | B45: Viewer read-only + has_ended gating across worker tabs: Add Worker, Resend Invites, Delete Invites and Export buttons are disabled for viewers and when opportunity.has_ended; opportunity_user_invite redirects with an error when has_ended. Src: workers.html (~36-78); opportunity_user_invite (~1527-1530). | G45: ✅ Automated (viewer half - Add Worker gated for a viewer): test_worker_gaps.py::test_src_w_47_viewer_read_only_gating. has_ended half needs an ended opp.
A46: GAP-SRC-W-48 | B46: Suspend modal + edge cases: modal shows a reason textarea plus pending_completed_work_count / payment_accrued / pending_payment warnings; re-suspending an already-suspended worker is idempotent; the suspended-users list page renders a Revoke column only for PM. Src: user_status_card.html (~43-94); suspend_user (~1441-1443); suspended_users_list (~1470-1493). | G46: ✅ Automated (suspended-users list Revoke column + listing): test_worker_gaps.py::test_src_w_48_suspended_users_list. Suspend-modal content + re-suspend idempotency deferred (modal path).
A47: GAP-SRC-W-49 | B47: Work Area Assignments tab appears only under the MICROPLANNING flag; the 6th worker tab is absent when the flag is off and the direct /workers/work-areas/ URL 404s. Src: BaseWorkerListView.get() tab append (~2646-2653); WorkerWorkAreaView.dispatch 404 (~2849-2852). | G47: ✅ Automated (positive - tab present + reachable under MICROPLANNING): test_worker_gaps.py::test_src_w_49_work_area_tab_present. Off-state (absent + 404) needs a non-microplanning opp.
A48: GAP-SRC-W-50 | B48: Cross-tab filter persistence: filters set on a worker sub-tab are saved to session and re-applied when navigating between worker tabs, but cleared when the page is entered from an unrelated page (referer check). Src: BaseWorkerListView.get_tabs / _is_navigating_between_tabs (~2598-2642). | G48: ✅ Automated (Playwright): test_worker_gaps.py::test_src_w_50_cross_tab_filter_persistence
A49: GAP-SRC-W-51 | B49: Deliver-tab count-breakdown popups are lazy hx-get to worker_flag_counts (status/payment_unit_id/access_id); the endpoint adds a 'Duplicate' bucket when saved_completed_count>1; the column-footer popup (no access_id) shows whole-opportunity totals; empty state 'No flagged visits'. Src: _render_flag_counts (~1610-1636); worker_flag_counts (~2910-2942); TotalFlagCountsColumn (~1456-1495). | G49: ✅ Covered by WLV_4/WLV_5 count-breakdown popups (test_worker_list_view.py per-worker + Total/footer). Duplicate bucket + "No flagged visits" empty state need specific data - deferred.
A50: GAP-SRC-W-52 | B50: Payments tab specifics: only rows with payment_accrued>=0 and accepted=True, ordered -payment_accrued; Accrued/Total Paid/Confirm headers are currency-code-suffixed and blank when no rows; footers sum accrued and total paid; last-paid history is a lazy popup ('--' when never paid); payment import is CSV/XLSX-only and cache-locked against concurrent imports. Src: WorkerPaymentsView (~2794-2820); WorkerPaymentsTable (~1173-1229); payment_import (~784-802). | G50: ✅ Automated (partial - currency-suffixed headers): test_worker_gaps.py::test_src_w_52_payments_currency_headers. Footer sums / import cache-lock eng-covered.

Sheet Visit verification page
A1: Network Manager
A2: Test Case ID | B2: Description | C2: Steps | D2: Outcome | E2: Status (Pass/Fail) | F2: QA Ticket | G2: Comments
A3: Worker Visit Verification Page_1 | B3: Confirm user lands on the Worker Visit Verification Page when they select a worker from the workers list page | C3: 1. Login to CCC web UI 2. Navigate to opp dashboard 3. Click on "connect workers" button 4. Select delivery tab 5. Click on the connect worker 6. User lands on the worker visits verification page | D3: - User should be able to land on the Worker Visit Verification page when they select any worker form the list - They should be able to review different type of visits under diff tabs that have been submitted on a given day - The list should contain the following columns i) Completion Time , Date ii) Entity Name iii) deliver unit iv) payment unit v) Last Activity vi) Status | G3: ✅ Automated: test_vv_01_land_and_bulk_approve (Playwright). Passing on stage.
A4: Worker Visit Verification Page_2 | B4: User should also view the worker's to date performance at the top of the page | C4: 1. Login to CCC web UI 2. Navigate to worker visit verification page | D4: - User should be able to view the workers performance at the top of the page and should see the following information (i) Total Visits: Payment units completed so far (ii) Pending Tasks (iii) Rejected Visits (iv) Accrued amount (v) Paid Amount | G4: ✅ Covered by test_worker_gaps.test_src_w_46_worker_profile_kpis (worker-profile KPI header).
A5: Worker Visit Verification Page_3 | B5: Confirm on selecting an image a pop-up should open with a carousel view | C5: 1. Login to CCC web UI 2. Navigate to worker visit verification page 3. Select any visit 4. Click on the image under visit details | D5: - User should be able to see the images in a carousel view when an image is selected | G5: ✅ Automated: test_vv_03_image_carousel. Skips when no scanned visit has a photo attachment - point WORKER_VISIT_VERIFICATION_PAGE_3 at a with-image visit to exercise it.
A6: Worker Visit Verification Page_4 | B6: Confirm user is able to suspend users from an opportunity | C6: 1. Login to CCC web UI 2. Navigate to opp dashboard 3. Click on "connect workers" button 4. Select delivery tab 5. Click on the connect worker 6. User lands on the worker visits verification page 7. Click on user name >> User details with suspend button pop up is displayed 8. Click on suspend button | D6: User should be able to suspend any worker from the opportunity by clicking the name of the user on the worker verification screen page | G6: ✅ Automated: test_vv_04_suspend_and_revoke. Passing on stage.
A7: Worker Visit Verification Page_5 | B7: Verify user is able to see two tabs: Visits and Tasks | C7: 1. Login to CCC web UI 2. Navigate to worker visit verification page | D7: - Visit details are shown in visits tab - Task details are shown in tasks tab | G7: ✅ Automated: test_vv_05_visit_tabs_render. Passing on stage.
A8: Worker Visit Verification Page_6 | B8: Verify submitted visit is auto approved | C8: 1. Login to CCC web UI 2. Invite a worker from an Opp 3. Submit few forms from mobile 4. Navigate to visit verification page | D8: - Submitted visit should get auto approved - Visit status should be approved
A9: Worker Visit Verification Page_7 | B9: Verify submitted visiit is auto rejected when doesn't satisfy the configured verification rules | C9: 1. Login to CCC web UI 2. For an opportunity configure verification rules 3. Submit the vists from mobile which doesn't satisfy the configured rules 4. Navigate to visit verification page | D9: - Visits that doesn't satisfy the configured verification rules are auto rejected
A10: Worker Visit Verification Page_8 | B10: Verify submitted visit is auto rejected when suspended user make a visit | C10: 1. Login to CCC web UI 2. Navigate to visit verification page >> Click on worker name >> Suspend the user 3. Submit few forms from mobile using user in step2 4. Observe the status of submitted visits in step3 | D10: - Visits that are submitted by suspended user are auto rejected
A11: Worker Visit Verification Page_9 | B11: Verify user is able to see the visit details upon clicking on the visit | C11: 1. Login to CCC web UI 2. Navigate to worker visit verification page 3. Select any visit | D11: - Following details are shown for visit details: Payment unit, Entity id, Entity name Verification Parameters Map | G11: ✅ Automated: test_vv_09_visit_details_panel. Passing on stage.
A12: Worker Visit Verification Page_10 | B12: Verify Over Limit status is marked correctly when visits exceeding the configured daily limit are submitted on the same day. | C12: 1. login to CCC web UI 2. Invite connect worker 3. Complete the daily limit visits in mobile 4. Again submit the visits exceeding the daily visit limit | D12: - visits submitted exceeding the daily visit limit should marked as over limit
A13: Worker Visit Verification Page_11 | B13: Verify only the first N visits (up to the daily limit) remain valid and any additional visits are flagged as Over Limit. | C13: 1. login to CCC web UI 2. Invite connect worker 3. Complete the daily limit visits in mobile 4. Again submit the visits exceeding the daily visit limit | D13: - visits submitted exceeding the daily visit limit should marked as over limit
A14: Worker Visit Verification Page_12 | B14: Verify Over Limit status is marked correctly when visits exceeding the configured total/max visit limit are submitted. | C14: 1. login to CCC web UI 2. Invite connect worker 3. Complete the total max limit visits in mobile 4. Again submit the visits exceeding the daily visit limit | D14: - visits submitted exceeding the total max limit should marked as over limit
A15: Worker Visit Verification Page_13 | B15: Verify only the first N visits (up to the total visit limit) remain valid and any additional visits are flagged as Over Limit. | C15: 1. login to CCC web UI 2. Invite connect worker 3. Complete the total max limit visits in mobile 4. Again submit the visits exceeding the daily visit limit | D15: - visits submitted exceeding the total max limit should marked as over limit
A16: Worker Visit Verification Page_14 | B16: Verify no additional visits are accepted when multiple submissions are processed concurrently after the daily limit has been reached. | C16: 1. Login to CCC Web UI. 2. Create an opportunity with a configured daily visit limit. 3. Invite multiple Connect workers or prepare multiple visit submissions from the same worker. 4. Submit visits until the daily limit is reached. 5. Immediately submit multiple additional visits concurrently (for example, back-to-back submissions from a single device, multiple devices, or queued submissions syncing together). 6. Navigate to the Worker Visit Verification page. | D16: - Visits submitted before the daily limit is marked as approved - visits submitted after the daily limit is marked as overlimit
A17: Worker Visit Verification Page_15 | B17: Verify no additional visits are accepted when multiple submissions are processed concurrently after the total visit limit has been reached. | C17: 1. Login to CCC Web UI. 2. Create an opportunity with a configured total/max visit limit. 3. Invite Connect workers. 4. Submit visits until the total visit limit is reached. 5. Immediately submit multiple additional visits concurrently (multiple devices, rapid submissions, or queued sync submissions). 6. Navigate to the Worker Visit Verification page. | D17: - Visits submitted before the total max limit is marked as approved - visits submitted after the total max limit is marked as overlimit
A18: Worker Visit Verification Page_16 | B18: Verify visits exceeding the daily limit are displayed with an Over Limit status on the Visit Verification screen. | C18: 1. Login to CCC Web UI. 2. Configure a daily visit limit for the opportunity. 3. Invite Connect workers. 4. Submit visits exceeding the configured daily visit limit. 5. Open the Worker Visit Verification page. 6. Locate visits marked as Over Limit. 7. Hover over the visit count indicator. | D18: - when mouse hover on the count of visits overlimit count should be displayed
A19: Worker Visit Verification Page_17 | B19: Verify visits exceeding the total visit limit are displayed with an Over Limit status on the Visit Verification screen. | C19: 1. Login to CCC Web UI. 2. Configure a total/max visit limit for the opportunity. 3. Invite Connect workers. 4. Submit visits exceeding the configured total visit limit. 5. Open the Worker Visit Verification page. 6. Locate visits marked as Over Limit. 7. Hover over the visit count indicator. | D19: - when mouse hover on the count of visits overlimit count should be displayed
A20: Worker Visit Verification Page_18 | B20: Verify the count of valid visits and Over Limit visits displayed on the Visit Verification screen is accurate after concurrent submissions. | C20: 1. Login to CCC Web UI. 2. Configure daily and total visit limits. 3. Invite Connect workers. 4. Submit multiple visits concurrently after the configured limit has been reached. 5. Open the Worker Visit Verification page. 6. Verify the visit summary counts. 7. Hover over the count indicators if applicable. | D20: - when mouse hover on the count of visits overlimit count should be displayed
A21: Worker Visit Verification Page_19 | B21: Verify visits submitted through queued/offline sync are correctly evaluated against the daily limit when multiple submissions are processed together. | C21: 1. Login to CCC Web UI. 2. Configure a daily visit limit. 3. Invite a Connect worker. 4. Put the mobile device in offline mode. 5. Submit multiple visits while offline, including submissions exceeding the daily limit. 6. Restore network connectivity and allow all queued visits to sync together. 7. Open the Worker Visit Verification page. | D21: - Visit that are in daily limit marked as approved - Visits that exceeds daily limit are marked as over limit
A22: Worker Visit Verification Page_20 | B22: Verify visits submitted through queued/offline sync are correctly evaluated against the total visit limit when multiple submissions are processed together. | C22: 1. Login to CCC Web UI. 2. Configure a total/max visit limit. 3. Invite a Connect worker. 4. Put the mobile device in offline mode. 5. Submit multiple visits while offline, including submissions exceeding the total visit limit. 6. Restore network connectivity and allow all queued visits to sync together. 7. Open the Worker Visit Verification page. | D22: - Visit that are in total/max limit marked as approved - Visits that exceeds total/max limit are marked as over limit
A23: Worker Visit Verification Page_21 | B23: Verify trial visit submission | C23: 1. Submit visits befor the opp start date | D23: - visits submitted before opp start date is marked as trial
A24: Worker Visit Verification Page_22 | B24: Verify post end date submissions | C24: 1. Submit the visits after the opp has ended | D24: - visits submitted after opp ended is not updated in web and no progress is gained for an opp
A25: Worker Visit Verification Page_23 | B25: Verify duplicate visits are billable only when visits are approved by NM and agreed by PM | C25: 1. Login to CCC web UI 2. Invite user for an Opp 3. Submit duplicate forms 4. Approve visit by NM user 5. Agree visit by PM user | D25: - Only forms that are approved by NM and agreed by PM are eligible for payment and amount should accrued | G25: This test is for opp created before june 1
A26: Worker Visit Verification Page_24 | B26: Verify duplicate visits are not billable when PM is not agreed | C26: 1. Login to CCC web UI 2. Invite user for an Opp 3. Submit duplicate forms 4. Approve visit by NM user | D26: - Visits that aren't agreed by Pm are not eligilble for payment | G26: This test is for opp created before june 1
A27: Worker Visit Verification Page_25 | B27: Verfiy the visits are billable only when agreed by PM using import bulk | C27: 1. Login to CC web UI 2. Invite user for an opp 3. Submit few duplicate visits 4. Navigate to connect workers page >> Download the PM review csv export 5. Make chnages are PM agreed for visits and import | D27: - Only forms that are approved by NM and agreed by PM are eligible for payment and amount should accrued | G27: This test is for opp created before june 1
A28: Worker Visit Verification Page_26 | B28: Verfiy the visits are not billable when disagreed by PM using import bulk | C28: 1. Login to CC web UI 2. Invite user for an opp 3. Submit few duplicate visits 4. Navigate to connect workers page >> Download the PM review csv export 5. Make chnages are PM disagreed for visits and import | D28: - Only forms that are approved by NM and agreed by PM are eligible for payment and amount should accrued | G28: This test is for opp created before june 1
A29: Worker Visit Verification Page_27 | B29: Verify combination of agreed/disgareed for duplicate visits using import | C29: 1. Login to CC web UI 2. Invite user for an opp 3. Submit few duplicate visits 4. Navigate to connect workers page >> Download the PM review csv export 5. Make chnages are PM agreed for few visits, disagree some visits and import | D29: - Only forms that are approved by NM and agreed by PM are eligible for payment and amount should accrued | G29: This test is for opp created before june 1
A30: Worker Visit Verification Page_28 | B30: Verify the invoice generating should contains only visits that are agreed by PM | C30: 1. Loin to CCC web UI 2. Navigate to view invoices page 3. Click create invoice >> service delivery 4. Select date | D30: - The visits that are approved by NM and agreed by PM are listed for invoice generation | G30: This test is for opp created before june 1
A31: Worker Visit Verification Page_29 | B31: Verify payment is accrued only when all required visits and atleast one optional visit (if any) are agreed by PM | C31: 1. Login to CCC web UI 2. Submit all required visits 3. Submit atleast one optioanl visit 4. Approve by NM and agree by PM | D31: - payment should be accrued only when all req visits and atleast one optional visit is agreed by PM | G31: This test is for opp created before june 1
A32: Worker Visit Verification Page_30 | B32: Verify payment is not accrued when all required visits and atleast one optional visit (if any) are agreed by PM | C32: 1. Login to CCC web UI 2. Submit all required visits 3. Submit atleast one optioanl visit 4. Approve by NM 5. Don't agree all visits by PM | D32: - payment should not be accrued | G32: This test is for opp created before june 1
A33: Worker Visit Verification Page_31 | B33: Verfiy user is able to reject the visits (NM user) | C33: 1. Login to CCC web UI 2. Navigate to visit verification page 3. Click on visit details >> Click on reject | D33: - Status should get update to rejected | G33: This test is for opp created before june 2 | ✅ Automated: test_vv_31_nm_reject_visit (NM org). Skips until a seeded manual-review opp with pending visits exists.
A34: Worker Visit Verification Page_32 | B34: Verify user is able to approve the visits (NM user) | C34: 1. Login to CCC web UI 2. Navigate to visit verification page 3. Click on visit details >> Click on approve | D34: - Status should get update to approved | G34: This test is for opp created before june 3 | ✅ Automated: test_vv_32_nm_approve_visit (NM org). Skips until a seeded manual-review opp with pending visits exists.
A35: Worker Visit Verification Page_33 | B35: Verify user is able to agree the visits (PM user) | C35: 1. Login to CCC web UI 2. Navigate to visit verification page 3. Click on visit details >> Click on agree | D35: - when PM approved visit paymnet amount is accrued | G35: This test is for opp created before june 4 | ✅ Automated: test_vv_33_pm_agree_visit. Skips until seeded NM-approved / PM-review-pending visits exist.
A36: Worker Visit Verification Page_34 | B36: Verify user is able to disagree the visits (PM user) | C36: 1. Login to CCC web UI 2. Navigate to visit verification page 3. Click on visit details >> Click on disagree | D36: - When PM disagreed no paymnet is accrued | G36: This test is for opp created before june 5 | ✅ Automated: test_vv_34_pm_disagree_visit. Skips until seeded NM-approved / PM-review-pending visits exist.
A37: Worker Visit Verification Page_35 | B37: Verify user is not able to agree the visit that is disagreed and vice versa | G37: ✅ Automated: test_vv_35_agree_and_disagree_are_mutually_exclusive (disagreed visit can't be agreed & vice-versa). Skips until manual-review opp seeded.
A38: Payment eligibility
A39: Payment eligibility_01 | B39: Verify user becomes eligible for payment when all required visits are approved | C39: 1. Login to CCC Web UI. 2. Create or select an opportunity with required delivery units configured. 3. Invite a PID user to the opportunity. 4. Login to the mobile app with the PID user. 5. Claim the job and submit forms for all required visits. 6. Approve the visits from the web/admin panel. | D39: User becomes eligible for payment once all required visits are approved.
A40: Payment eligibility_02 | B40: Verify user is not eligible for payment if any required visit is not approved | C40: 1. Login to CCC Web UI. 2. Create an opportunity with multiple required visits. 3. Invite a PID user. 4. Submit all required visits from mobile. 5. Approve only some of the required visits and leave at least one pending/rejected. | D40: User should not be eligible for payment if any required visit is not approved.
A41: Payment eligibility_03 | B41: Verify payment eligibility when all required visits and at least one optional visit are approved | C41: 1. Create an opportunity with required and optional delivery units. 2. Invite PID user and claim job from mobile. 3. Submit required visit forms. 4. Submit at least one optional visit form. 5. Approve all required visits and one optional visit. | D41: User becomes eligible for payment.
A42: Payment eligibility_04 | B42: Verify worker is not eligible if optional visits exist but none are approved | C42: 1. Create opportunity with required and optional visits. 2. Submit all required visits. 3. Submit optional visits but do not approve them. 4. Approve only required visits. | D42: User should not be eligible for payment because no optional visit is approved.
A43: Payment eligibility_06 | B43: Verify auto-approval system correctly marks eligibility | C43: 1. Enable auto approval for visits. 2. Invite PID user. 3. Submit required and optional visits from mobile. 4. Allow system to auto approve visits. | D43: System automatically marks user as eligible for payment when conditions are satisfied.
A44: Payment eligibility_07 | B44: Verify manual approval works with new eligibility logic | C44: 1. Create opportunity with required and optional visits. 2. Submit visits from mobile. 3. Admin manually approves required visits and at least one optional visit. | D44: User becomes eligible for payment after manual approval.
A45: Payment eligibility_08 | B45: Verify optional visit approved but required visits missing | C45: 1. Create opportunity with required and optional visits. 2. Submit optional visit first. 3. Approve optional visit but leave required visits pending. | D45: User should not be eligible for payment until all required visits are approved.
A46: Payment eligibility_09 | B46: Verify rejected visits do not count toward payment eligibility | C46: 1. Submit required visits from mobile. 2. Reject one of the required visits from web. | D46: User should not be eligible for payment when a required visit is rejected.
A47: GAP-SRC-W-40 | B47: Verification tab-set is a function of mode x role: auto+PM=[All]; auto+NM=[Approved,Rejected,All]; manual+PM=[Pending PM Review,Disagree,Agree,All]; manual+NM=[Pending NM Review,Pending PM Review,Disagree,Agree,Rejected,All]. Tab labels are role-sensitive (agree='Agree'(PM)/'Approved'(NM); disagree='Disagree'(PM)/'Revalidate'(NM)). Src: VisitVerificationTableView.tabs + get_tab_display (views.py ~2355-2384). | G47: ✅ Automated: test_gap_w_40_verification_tab_set_by_mode_and_role. Asserts PM sees Pending PM Review (not Pending NM Review), NM sees both, set ends with 'All'. Skips until manual-review opp seeded / when WORKER_VISITS_TASKS switch ON.
A48: GAP-SRC-W-41 | B48: WORKER_VISITS_TASKS waffle switch changes the whole visit table: ON -> plain WorkerVisitTable (no review tabs, no bulk actions); OFF -> tabbed VisitVerificationTable. Also gates the Visits/Tasks sub-tab bar on the worker profile. Src: visit_verification_table_view (~2436-2441); UserVisitVerificationView show_worker_tasks_tabs (~2190). | G48: ✅ Automated: test_gap_w_41_visit_table_waffle_mode_consistent. Passing on stage.
A49: GAP-SRC-W-42 | B49: In-UI bulk Approve/Reject rules: max 100 visits per bulk op (400 'Maximum 100 visits allowed'); justification mandatory for flagged visits; reject requires a reason; disagree->pending; payment accrued recomputed. Src: approve_visits (~1062-1109) / reject_visits (~1116-1136). | G49: ✅ Automated (partial): test_gap_w_42_reject_requires_reason + test_gap_w_42_approve_requires_justification (mandatory reason/justification enforced). 100-visit bulk cap NOT covered (needs >100 seeded visits).
A50: GAP-SRC-W-43 | B50: Bulk select + Approve All/Reject All controls are hidden for PM, for viewer, and under auto-verify; only a non-viewer NM on a manual-review opp sees them. The select checkbox column is invisible for PM. Src: user_visit_verification_table.html bulk button guards; UserVisitVerificationTable.__init__ select column (~915-917). | G50: ✅ Automated: test_gap_w_43_bulk_controls_hidden_for_pm (passing). NM positive control test_gap_w_43_bulk_controls_visible_for_nm skips until a seeded manual-review opp.
A51: GAP-SRC-W-44 | B51: Individual visit-review action bar is role/mode gated: hidden entirely under auto-verify; PM sees Agree/Disagree (Disagree only when review pending; Agree disabled when already agree); NM sees Approve/Reject with enable/disable by status; all disabled for viewer. Src: user_visit_details.html action bar (~292-320); user_visit_review (~1547-1557). | G51: ✅ Automated: test_gap_w_44_visit_action_bar_gating. Passing on stage.
A52: GAP-SRC-W-45 | B52: Manual-verification endpoints (approve/reject/review/import-review/export-review) return HTTP 403 + HX-Trigger reload_table when the opportunity is auto-verify. Src: @require_manual_visit_verification (decorators.py ~6-27). | G52: ✅ Automated: test_gap_w_45_manual_endpoint_403_under_auto_verify. Skips on covid_opp_test (it is manual-review, not auto-verify) - needs an auto-verify opp to run the 403 assertion.

Sheet Invoices List page
A1: Network Manager
A2: Test Case ID | B2: Description | C2: Steps | D2: Outcome | E2: Status (Pass/Fail) | F2: QA Ticket | G2: Comments
A3: Invoice_01 | B3: Verify user can land on the Invoice page by clicking "View Invoice" option from the opportunity dashboard page | C3: 1. Login to CCC web UI 2. Navigate to opp dashboard 3. Click on hamburger option 4. Select "view invoice" option | D3: - User should land on the Invoices page without any issue - They should see a list of previous invoices which by default is ordered by the date in which it was raised. - They should see the following two tabs on the Invoices page: All Invoices Payment Report - User should also see a "Create new Invoice" button
A4: Invoice_02 | B4: Verify user sees all the information for invoices under All Invoice tab | C4: 1. Login to CCC web UI 2. Navigate to opp dashboard 3. Click on hamburger option 4. Select "view invoice" option | D4: User should the following columns on the "All Invoices" tab - Amount - Amount (USD) - Rate - Date added - Invoice Number - Payment Status - Payment Date - Service Delivery
A5: Invoice_03 | B5: Verify user sees the total accrued and paid amount for both worker and organization on the Payment Report page | C5: 1. Login to CCC web UI 2. Navigate to opp dashboard 3. Click on hamburger option 4. Select "view invoice" option 5. Go to payment report tab | D5: - User should see the total amount accrued by both Workers and Organization - User should also see total amount paid to both Workers and Organization - User should see a button to switch to USD from local currency - User should see the following columns on the page Payment Unit Approved Units User Payment Accrued Network Manager Payment Accrued
A6: Invoice_04 | B6: Verify on the Payment Report, the amount gets converted to USD when user toggles the switch | C6: 1. Login to CCC web UI 2. Navigate to opp dashboard 3. Click on hamburger option 4. Select "view invoice" option 5. Go to payment report tab 6. Click on USD | D6: - The amount should get updated to USD from local currency when the user toggles the switch to USD from local currency
A7: Invoice_05 | B7: Confirm user can create a new custom invoice by clicking on the "Create Invoice" button | C7: 1. Login to CCC web UI 2. Navigate to opp dashboard 3. Click on hamburger option 4. Select "view invoice" option 5. click on create invoice button and Select Invoice Type = Custom 6. Enter Invoice Amount 7. Enter Date of Expense Incurred 8. Enter Justification describing purpose, date, and subscription 9. Click Submit | D7: "- User is navigated to Custom Invoice page - Invoice ID is unique and auto generated - Invoice Generation Date is auto generated today's date - Required fields are validated - Custom invoice is created successfully - Invoice appears in Invoice List with Invoice Type = Other" ii) Enter all the details and ensure a new invoice get created and is visible under "All Invoices" tab. iii) Invoice should also be visible for a PM user
A8: Invoice_06 | B8: Confirm that user sees a message, displaying the amount in USD | C8: 1. Login to CCC web UI 2. Navigate to opp dashboard 3. Click on hamburger option 4. Select "view invoice" option 5. On invoice page, click on create invoice button 6. Create an invoice | D8: - On entering the amount in the amount field, user should see the following message Exchange Rate on 20-06-2025: 'xyz' Amount in USD: 'abc' - On creating the invoice, user should see the amount in both local currency and USD on the "All Invoices" tab Note: When the program is created in USD, user should see the message but the amount after exchange rate should be same as entered by the user.
A9: Invoice_07 | B9: Verify mandatory fields for Custom Invoice | C9: 1. Login as NM 2. Navigate to Create Custom Invoice 3. Leave Amount field blank 4. Click Submit 5. Repeat by leaving Justification field and date of expense incurred field blank | D9: - System displays "please fil this field" error message - Invoice is not submitted until all required fields are completed
A10: Invoice_08 | B10: Verify invoice status is show as "pending Network Manager Review" upon new invoice creation | C10: 1. Login to CCC web UI 2. Navigate to Opp dashboard 3. Hamgurger menu >> view invoices >> create invoice | D10: Invoice has been created and Invoice status is shown as "Pending Network manager review" on the invoices list page
A11: Invoice_09 | B11: Verify user is able to submit inovice to program manager [NM user] | C11: cont to above TC - Click on review button - Click on Submit to program manager button | D11: -"Invoice has been submitted for approval" message is displayed - Invoice status should be shown as " Pending Program manager review" on invoices list page
A12: Invoice_10 | B12: Verify user is able to cancel the invoice as network manager | C12: 1. Login to CCC web UI 2. Navigate to Opp dashboard 3. Hamgurger menu >> view invoices >> create invoice 4. Click on review >> Click cancel 5. On the cancel invoice pop up click on the cancel invoice button | D12: - Cancel invoice pop up is displayed with follwoing details: "Are you sure you want to cancel this invoice? This action cannot be undone." message and Close and Cancel invoice buttons - "Invoice has been cancelled by Network Manager" message is displayed - Invoice status should be "Cancelled by NM"
A13: Invoice_11 | B13: Verify NM user is not able to cancel the invoice by clicking on close button on the invoice pop up | C13: 1. Login to CCC web UI 2. Navigate to Opp dashboard 3. Hamgurger menu >> view invoices >> create invoice 4. Click on review >> Click cancel 5. On the cancel invoice pop up click on the close button | D13: - Cancel invoice pop up is displayed with follwoing details: "Are you sure you want to cancel this invoice? This action cannot be undone." message and Close and Cancel invoice buttons - When click on the close button, user lands on the invoice review page
A14: Invoice_12 | B14: Verify user is able to see the invoice status as "pending program manager review" after submited to PM | C14: 1. Login to CCC web UI 2. Navigate to Opp dashboard 3. Hamgurger menu >> view invoices >> create invoice 4. Click on review >> Click on "submit to program manager" | D14: - "Pending program manager review" status is shown as invoice type on the invoice list page
... A31: Invoice_29 | B31: Verify user is able to edit the service delivery notes on the review page as NM user | C31: 1. Login to CCC web UI 2. Navigate to Opp dashboard 3. Hamgurger menu >> view invoices >> create invoice 4. Click on review 5. On review page, edit the service delivery notes and submit to PM | D31: - User should be able to edit the service delivery notes
A32: Program Manager
A33: Invoice List_30 | B33: Confirm user can see a list of all the invoices for an opportunity | C33: 1. Login to CCC web UI 2. Navigate to opp dashboard 3. Click on hamburger option, view invoices option | D33: - User should be able to see a list of all the invoices generated by clicking the View Invoices menu option in the Opportunity dashboard or the Opportunity list
A34: Invoice List_31 | B34: Verify user is able to see the invoice status as "pending program manager review" after submited to PM | C34: 1. Login to CCC web UI 2. Navigate to Opp dashboard 3. Hamgurger menu >> view invoices >> create invoice 4. Click on review >> Click on "submit to program manager" | D34: - "Pending program manager review" status is shown as invoice type on the invoice list page
A35: Invoice List_32 | B35: Verify user should see the Approval for payment processing option as PM user | C35: Cont to above TC - Click on review button as PM user - Click on "Approve for payment processing" button | D35: - "Invoice has been approved and ready to pay" message is displayed - Invoice status is changed as "ready to pay"
A36: Invoice List_33 | B36: Verify user is able to reject the invoice when invoice is in ready to pay status | C36: Cont to above TC - Click on review >> Click on reject button - Reject invoice pop is displayed >> click on reject invoice option | D36: - Reject invoice pop up is displayed with follwoing details: "Are you sure you want to reject this invoice? This action cannot be undone." message and Close and reject invoice buttons - When click on the reject inovice button, "Invoice has been rejected by Project Manager" message is displayed - Invoice status should be changed to "Rejected by PM"
A37: Invoice List_34 | B37: Verify PM user is not able to reject the invoice by clicking on close button on the reject invoice pop up | C37: 1. Login to CCC web UI 2. Navigate to Opp dashboard 3. Hamgurger menu >> view invoices >> create invoice 4. Submit to PM and approve for payment processing >> Click on review >> reject 5. On the reject invoice pop up click on the close button | D37: - Reject invoice pop up is displayed with follwoing details: "Are you sure you want to reject this invoice? This action cannot be undone." message and Close and reject invoice buttons - When click on the close button, user lands on the invoice review page
A38: Invoice List_35 | B38: Verify PM user is able to reject the invoice | C38: 1. Login to CCC web UI 2. Navigate to Opp dashboard 3. Hamgurger menu >> view invoices >> create invoice 4. Click on review >> Click Submit for PM 5. As Pm user, click on review >> click reject 5. On the reject invoice pop up click on the reject invoice button | D38: - Reject invoice pop up is displayed with follwoing details: "Are you sure you want to reject this invoice? This action cannot be undone." message and Close and reject invoice buttons - When click on the reject inovice button, "Invoice has been rejected by Project Manager" message is displayed - Invoice status should be changed to "Rejected by PM"
A39: Invoice List_36 | B39: Verify PM user is able to pay the invoice | C39: 1. Login to CCC web UI 2. Navigate to Opp dashboard 3. Hamgurger menu >> view invoices >> create invoice 4. Click on review >> Click on "submit to program manager" >> Click on "Approve for payment processing" 5. Click on review >> user should see pay button >> Click on pay button | D39: - Invoice has been paid and email is triggered. - Invoices status changes to "paid"
A40: Invoice List_37 | B40: Verify user is able to review the invoice in read only mode as PM user | C40: 1. Login to CCC web UI as PM 2. Navigate to Opp dashboard 3. Hamgurger menu >> view invoices >> create invoice 4. Click on review 5. Verify user is not able to edit the invoice details | D40: - User should see the invoice review in read only mode

Sheet Connect Messaging
A1: Prerequsite: A PID user should get created and login to the learn app, submit few forms.
A2: Test Case ID | B2: Description | C2: Steps | D2: Outcome | E2: Status (Pass/Fail) | F2: QA Ticket | G2: Comments
A3: Connect channel 1 | B3: Verify user is able to create connect channel | C3: 1. Login to CC hq 2. Navigate to messaging >> view all 3. Under connect messaging section, Select user conset 4. Click Request messaging consent button | D3: - Channel created for a personal ID message is displayed on hq web - Channel should get created and displayed in the connect mobile
A4: Connect message1 | B4: Verify user is able to create a broadcast with connect message option | C4: 1. Login to CC hq 2. Navigate to Messaging >> Broadcasts 3. Click on "+ Add broadcast" 4. Select the content type as 'connect message' 5. Create a broadcast 6. Verify PID user recive a message on the channel | D4: - User should be able to receive the broadcast message in the connect channel
A5: Connect message2 | B5: Verify user is able to create a broadcast with connect survey option | C5: 1. Login to CC hq 2. Navigate to Messaging >> Broadcasts 3. Click on "+ Add broadcast" 4. Select the content type as 'connect Survey' 5. Create a broadcast 6 Verify PID user recive a message on the channel | D5: - User should be able to receive the broadcast survey in the connect channel - User should be able to answer the question and get next question in the form - Form should get submit and able to verify it on the submit histstory
A6: Connect message3 | B6: Verify all the options from Recipents dropdown is disabled except users upon selecting message type as connect message/survey | C6: 1. Login to CC hq 2. Navigate to Messaging >> Conditional alert or Broadcast 3. Click on "+Add Broadcast" 4. Select the content type as 'connect survey' / 'Connect messaging' 5. Verify all the options in the recipents dropdown is disabled and only users option is available | D6: - Only users option should be visible and preselected upon selecting the connect message/survey option
A7: Connect message4 | B7: Verify user is able to create a Conditional alerts with connect message option | C7: 1. Login to CC hq 2. Navigate to Messaging >> Conditional alert 3. Click on "+ Conditional alert" 4. Select the content type as 'connect message' 5. Create a Conditional alert 6. Submit a form with PID user used to create CA by satisfying the alert condition 7 Verify PID user recive a message on the channel | D7: - User should be able to get a alert message in the connect channel upon submitting the form satisfying the alert condition
A8: Connect message5 | B8: Verify user is able to create a conditional alerts with connect survey option | C8: 1. Login to CC hq 2. Navigate to Messaging >> Conditional alert 3. Click on "+ Conditional alert" 4. Select the content type as 'connect survey' 5. Create a Conditional alert 6. Submit a form with PID user used to create CA by satisfying the alert condition 7 Verify PID user recive a message on the channel | D8: - User should be able to get a alert survey message in the connect channel upon submitting the form satisfying the alert condition - User should be able to answer the question and get next question in the form - Form should get submit and able to verify it on the submit histstory
A9: Connect message6 | B9: Verify all the options from Recipents dropdown is disabled except users upon selecting message type as connect message/survey | C9: 1. Login to CC hq 2. Navigate to Messaging >> Conditional alert or Broadcast 3. Click on "+ Conditional alert" 4. Select the content type as 'connect survey' / 'Connect messaging' 5. Verify all the options in the recipents dropdown is disabled and only users option is available | D9: - Only users option should be visible and preselected upon selecting the connect message/survey option
A10: Connect message7 | B10: Verify user is able to select only active PID users while creating a Conditional alerts with connect message/survey options | C10: Continue to above TC: Also verify only the active PID users are present in the | D10: - Only the PID users data should get display on the users drop down
A11: Connect message8 | B11: Verify user is able to create keyword for connect message | C11: 1. Login to CC hq web UI 2. Navigate to Messaging >> keyword 3. Select 'connect message' as content type 4. Create a keyword 5. Login with personal ID [CCC mobile] 5. Trigger keyword from channel 6. verify user receive a connect message in the channel to the personal ID user | D11: - User should get a connect message in the channel upon triggering the keyword
A12: Connect message9 | B12: Verify user is able to create keyword for connect survey | C12: 1. Login to CC hq web UI 2. Navigate to Messaging >> keyword 3. Select 'connect survey' as content type 4. Create a keyword 5. Login with personal ID [CCC mobile] 5. Trigger keyword from channel 6. verify user receive a first question from the form in the channel to the personal ID user 7. Answer all the questions for the form 8. Verify that submitted form is present on hq | D12: - User should be able to get a connect survey from in the connect channel upon triggering the keyword in the channel - User should be able to answer the question and get next question in the form - Form should get submit and able to verify it on the submit histstory

Sheet Delivery Reminder Mails
A1: Test Case ID | B1: Description | C1: Steps | D1: Outcome | E1: Status (Pass/Fail) | F1: QA Ticket | G1: Comments
A2: Review mail_01 | B2: Verify reminder mail is sent for all the members of organization regarding pending review deliveries for all the opportunities | C2: 1. Ensure an organization has one or more opportunities with pending deliveries. 2. Ensure multiple users are added as members of the organization. 3. wait for the scheduled reminder task to run. 4. Check inboxes of all organization members. | D2: - Reminder email is sent to all organization members. - Email displays all opportunities that have pending deliveries.
A3: Review mail_02 | B3: Verify no mail is triggered when no pending visits are there for any of the opportunities user is a member | C3: 1. Ensure the organization has no opportunities with pending deliveries. 2. wait for the scheduled reminder task to run. 3. Check inboxes of all organization members. | D3: - No reminder emails are sent to the organiztion memebers
A4: Review mail_03 | B4: Verify reminder email contains a valid link to the workers list delivery tab page | C4: 1. Open the reminder email received by an organization member. 2. Locate the Workers List link in the email. 3. Click the link. | D4: - Link is present, clickable, and redirects to the correct Workers List page. - Only opportunities with pending deliveries are included in the email.
A5: Review mail_04 | B5: Verify that the Opportunities list link redirects to the Connect Workers Delivery tab | C5: 1. Open the reminder email. 2. Click on the Opportunities list link. 3. Observe the landing page. | D5: User is redirected to the Connect Workers Delivery tab.
A6: Review mail_05 | B6: Verify following details are included in reminder mail: Organization name and list of opportunities with redirect link | C6: 1. Trigger the reminder email 2. Open the email. 3. Verify organization name, opportunity names, and links is displayed. 4. Verify list of opportunities with pending deliveries is shown. | D6: Following details in the email should be accurate and up to date. - Organization Name - Opportuntiy Name - Links "Reminder email includes following things: - Message saying ""This is a reminder to review pending deliveries before the end of the month so they can be included in invoices"" - Organization name - List of pending opportunities."
A7: Review mail_06 | B7: Verify mail is not triggered to the members who are not a part of organization | C7: 1. Identify users who are not members of the organization. 2. Ensure organization has pending deliveries. 3. Trigger the reminder email. 4. Check inboxes of non-members. | D7: Reminder email is not sent to non-organization members.
A8: Review mail_07 | B8: Verify opportunities which have only PM pending review will be included only in PM organization reminder mail | C8: 1. Ensure opportunities have PM pending reviews. 2. Trigger the PM reminder email job. 3. Open the PM reminder email. | D8: Opportunities with PM pending reviews are included in the PM reminder email.
A9: Review mail_08 | B9: Verify opportunities that have only NM review will be included only in NM organization reminder mail | C9: 1. Ensure opportunities have NM pending reviews. 2. Trigger the NM reminder email job. 3. Open the NM reminder email. | D9: Opportunities with NM pending reviews are included in the NM reminder email.

Sheet App Credentials
A1: Test Case ID | B1: Description | C1: Steps | D1: Outcome | E1: Status (Pass/Fail) | F1: QA Ticket | G1: Comments
A2: Credentials_1 | B2: Verify user is able to select an application for Issueing Credentials on HQ | C2: 1. Login to CC HQ :https://staging.commcarehq.org/a/connectqa/settings/project/credentials_application// 2. Navigate to project settings 3. Under project administration select credentials Applications 4. Select any app the form the dropdown | D2: User should be able to select any app from the dropdown list to issue credentials.
A3: Credentials_2 | B3: Confirm that we see the Worker Activity option for the selected app | C3: continue to above TC: - Go to the app settings for the app used in above TC | D3: - User should see the option for Worker Activity under Advanced Settings only for the selected app. - User should be able to select any of the options from the dropdown list.
A4: Credentials_3 | B4: Verify that the profile.xml is updated for the app | C4: 1. Go to app release page 2. Clcik on publish 3. Click on View source file 4. Select profile.xml | D4: User should see the workers activity in the profile.xml file with the correct values for the worker activity.

Sheet Re-Learn Task
A1: Test Case ID | B1: Description | C1: Steps | D1: Outcome | E1: Status (Pass/Fail) | F1: QA Ticket | G1: Comments
A2: Re-Learn_01 | B2: Verify user is able to configure task type question in CC hq app | C2: 1. Navigate to CC hq >> delivery app 2. Add question type as advanced>> task | D2: - User should be able to create a task type question in hq app
A3: Re-Learn_02 | B3: Verify user is able to configure task type for an Opp | C3: 1. Naviagte to opp dashboard >> Hamburger option >> configure task types 2. Click on "+Add new task type" 3. New task type pop up is dispalyed , select the following details: - Task unit, Name, Case property and description 4. Click on save | D3: - User should be able to see the configured task type on the list
A4: Re-Learn_03 | B4: Verify available tasks are listed as dropdown under task unit field | C4: 1. Naviagte to opp dashboard >> Hamburger option >> configure task types 2. Click on "+Add new task type" 3. click on available tasks field | D4: - A dropdown should be displayed containing the tasks configured on hq app
A5: Re-Learn_04 | B5: Verify that the Name field is mandatory | C5: 1. Naviagte to opp dashboard >> Hamburger option >> configure task types 2. Click on "+Add new task type" 3. Save the task type without entering the name | D5: - User should see the error "fill in this field" for name field
A6: Re-Learn_05 | B6: Verify that the Description field validation is displayed when left empty | C6: 1. Naviagte to opp dashboard >> Hamburger option >> configure task types 2. Click on "+Add new task type" 3. Save the task type without entering the description | D6: - User should see the error "fill in this field" for description field
A7: Re-Learn_06 | B7: Verify that the user is able to configure a task type even when the case property is not entered | C7: 1. Naviagte to opp dashboard >> Hamburger option >> configure task types 2. Click on "+Add new task type" 3. Save the task type without entering the case property | D7: - User should be able to configure task type successfully
A8: Re-Learn_07 | B8: Verify the validation for the Task Unit field | C8: 1. Naviagte to opp dashboard >> Hamburger option >> configure task types 2. Click on "+Add new task type" 3. Save the task type without selecting the task field | D8: - User should see "Please select an item in the list" error for task unit field
A9: Re-Learn_08 | B9: Verify that the user is able to cancel the task configuration by clicking the Cancel button | C9: 1. Naviagte to opp dashboard >> Hamburger option >> configure task types 2. Click on "+Add new task type" 3. Enter all the details 4. Click cancel | D9: - New task type creation template should get close and no task type is configured
A10: Re-Learn_09 | B10: Verify user is able to close the task configuration when click on the "x"(Close) button | C10: 1. Naviagte to opp dashboard >> Hamburger option >> configure task types 2. Click on "+Add new task type" 3. Enter all the details 4. Click on "X" close button | D10: - New task type creation template should get close and no task type is configured
A11: Re-Learn_10 | B11: Verify that the user is able to edit the configured task | C11: 1. Naviagte to opp dashboard >> Hamburger option >> configure task types 2. On the task type list page, click on the edit button 3. On edit task type template, edit name and description 4. Click save | D11: - User should be able to edit the configured task type - Edited Changes should be saved successfully
A12: Re-Learn_11 | B12: Verify user is able to archive the configured task | C12: 1. Naviagte to opp dashboard >> Hamburger option >> configure task types 2. On the task type list page, click on the edit button under actions column 3. On edit task type template, select the check box under archive this task type 4. Click save | D12: - Task should get archieved succesfully and archieved date should get updated - Archieved tasks are not shown on connect workers >> tasks - User shouldn't be able to assign new tasks
A13: Re-Learn_12 | B13: Verify user is able to sort the tasks using "task type name" header sorting arrows | C13: 1. Naviagte to opp dashboard >> Hamburger option >> configure task types 2. Click on the sort arrows at "task type name" header | D13: -Task list should get sort upon clicking on the arrows
... A39: Re-Learn_38 | B39: Verify user is able to sort details by headder arrows | C39: 1. On Opp dashboard >> click on "tasks assigned to connect workers" 2. On tasks list page >> Click on headder arrows | D39: - List should be sort by clicking on arrow headders

Sheet Microplanning
A1: prerequisite - Microplanning feature flag should be enabled for managed opportunity
A2: Test Case ID | B2: Description | C2: Steps | D2: Outcome | E2: Status (Pass/Fail) | F2: Ticket/ Bug | G2: Comments
A3: Microplanning_01 | B3: Verify user is able to land on select opportunity area page(microplanning) | C3: 1. Login to CCC web UI 2. On Opp dashboard, click on "View progress map" button | D3: - User should land on select opp area page
A4: Microplanning_02 | B4: Verify user is able to cluster work areas | C4: 1. Login to CCC web UI 2. On Opp dashboard, click on "View progress map" button 3. Click on "create work area groups" | D4: - Uploaded work areas are grouped together as clusters based on backend code - User should see the colours for the work areas after clustering
A5: Microplanning_03 | B5: Verify user is able to download the work area summary | C5: 1. Login to CCC web UI 2. On Opp dashboard, click on "View progress map" button 3. At filter map work areas section, click on download arrow button | D5: - File should get downloaded with work area summary - If filters are applied, file should get downloaded with work area details based on filters
A6: Microplanning_04 | B6: Verify Filter Map work Areas | C6: 1. Login to CCC web UI 2. On Opp dashboard, click on "View progress map" button 3. Observe the filter map work areas | D6: - Following fields should be visible under filter map work areas: Show visits toggle button Work Areas status Assignee Start date End date Show only unassigned section
A7: Microplanning_05 | B7: Verify show visits option under filter map work areas | C7: 1. Login to CCC web UI 2. On Opp dashboard, click on "View progress map" button 3. Under filter map work areas section, enable show visits button | D7: - If show visits is on, user should see the submitted visits in the map - If it is off, no visits are shown on map
A8: Microplanning_06 | B8: Verify show only unassigned option | C8: 1. Login to CCC web UI 2. On Opp dashboard, click on "View progress map" button 3. Under filter map work areas section, Click on the dropdown of show only unassigned option | D8: - Following options should be available for show only unassigned option: Unknown Yes No - If yes is selected, only unassigned visits are highlighted - If No is selected, all visits are shown
A9: Microplanning_07 | B9: Verify work area status field | C9: 1. Login to CCC web UI 2. On Opp dashboard, click on "View progress map" button 3. Under filter map work areas section, Click on work area status field | D9: Following options are visible for work area status field: - Not Started - Unassigned - Not visited - Visited - Request for inaccessible - Inaccesible - Excluded - Expected visit count User should be able to select multiple options from the dropdown
A10: Microplanning_08 | B10: Verify user is able to see the work areas highlighted based on selected status | C10: 1. Login to CCC web UI 2. On Opp dashboard, click on "View progress map" button 3. Under filter map work areas section, Click on work area status field 4. Select the options from work area status field | D10: - Work areas should get based on selected options
A11: Microplanning_09 | B11: Verify user is able to review the inaccessible request | C11: 1. Assign work area to user 2. From mobile request work area for inaccesible 3. On Opp dashboard, click on "View progress map" button 4. Select the work area used in step 2 4. Under work area details click on review inaccessible button | D11: Follwoing details are observed on the review pop up: - Visit date - Reason - Location - Photo evidence - Return to progress map button - Deny request button - Approve as inaccessible
A12: Microplanning_10 | B12: Verify user is able to approve the inaccessible request | C12: cont to above TC - Click on deny button | D12: - Push notification is sent to mobile that request for inaccesibility is denined - Work area status will update accordingly in web
A13: Microplanning_11 | B13: Verify user is able to deny the inaccessible request | C13: 1. Assign work area to user 2. From mobile request work area for inaccesible 3. On Opp dashboard, click on "View progress map" button 4. Select the work area used in step 2 4. Under work area details click on review inaccessible button 5. on review pop up, click on approve as inaccessible | D13: - Work area is marked as inaccessible
A14: Microplanning_12 | B14: Verify assignee field | C14: 1. Login to CCC web UI 2. On Opp dashboard, click on "View progress map" button 3. Under filter map work areas section, Click on assignee field | D14: Assignee field dropdown should contain only the workers list that are assigned for work areas
... A27: Microplanning_25 | B27: Verify select new assignee dropdown contains all the connect workers | C27: 1. Login to CCC web UI 2. On Opp dashboard, click on "View progress map" button 3. Click on enter assignment mode 4. Click on "select FLW" field, under 'Select new Assignee' section | D27: - User should see the list of connect workers under select new assignee field
A28: Microplanning_26 | B28: Verify user is able to asssign multiple workers in signle action | C28: 1. Login to CCC web UI 2. On Opp dashboard, click on "View progress map" button 3. Click on enter assignment mode 4. Select work area/areas to be assigned 5. Click on "select FLW" field, under 'Select new Assignee' section 6. Select one connect worker >> click save button 7. Again select another worker >> click save button
A29: Microplanning_27 | B29: Verify FLW summary | C29: 1. Login to CCC web UI 2. On Opp dashboard, click on "View progress map" button 3. Click on enter assignment mode 4. Select work area/areas to be assigned 5. Click on "select FLW" field, under 'Select new Assignee' section 6. Select one connect worker under FLW section 7. Observe FLW summary details are visible | D29: Following details are Shown under FLW summary when FLW is selected: - Count of Assigned Buildings - Count of Assigned Visits - Count of Assigned Work Areas - view summary by FLW button - View Visits button
A30: Microplanning_28 | B30: Verify user lands on work area assignments page when clicking on view summary by FLW button | C30: 1. Login to CCC web UI 2. On Opp dashboard, click on "View progress map" button 3. Click on enter assignment mode 4. Select work area/areas to be assigned 5. Click on "select FLW" field, under 'Select new Assignee' section 6. Select one connect worker under FLW section 7. Click 'View summary by FLW' button | D30: - User should land on the work area assignments page
A31: Microplanning_29 | B31: Verify user lands on visits page when clicking on view visits button | C31: 1. Login to CCC web UI 2. On Opp dashboard, click on "View progress map" button 3. Click on enter assignment mode 4. Select work area/areas to be assigned 5. Click on "select FLW" field, under 'Select new Assignee' section 6. Select one connect worker under FLW section 7. Click 'View Visits" button | D31: - User should land on the connect workers page
A32: Microplanning_30 | B32: Verify details on opp card [microplanning page] | C32: 1. Login to CCC web UI 2. On Opp dashboard, click on "View progress map" button 3.Verify work area details on top of the page | D32: Following details are shown: - Days Remaining - Unvisited Work Areas - Visited Work Areas - EVC Reached - Inaccessible Work Areas - Excluded Work Areas - WA visited : Visits ratio - Coverage see more button
A33: Microplanning_31 | B33: Verify user is able to land on progress tracker page upon clicking on coverage(see more) button on microplanning page | C33: 1. Navigate to Opp dashboard 2. Click on View progress map button 3. click on coverage see more button | D33: - User should be able to land on progress tracker page
A34: Microplanning_32 | B34: Verify metrics count on microplanning page matches the work areas | C34: 1. Login to CCC web UI 2. On Opp dashboard, click on "View progress map" button 3.Verify work area details on top of the page 4. Apply filters and verify the count matches the work areas highlighted | D34: - Metrics count should match with the work areas highlighted
A35: Microplanning_33 | B35: Verify assigned work areas are shown under work area assignments tab | C35: 1. Navigate to Opp dashboard 2. Click on connect workers button 3. Navigte to work area assignment tabs on connect workers page | D35: Follwoing details are shown on work area assignment tabs: - Name - Last active - Assigned Buildings - Assigned Visits - Assigned work areas - Assigned work area groups - visits done
A36: Microplanning_34 | B36: Verify user should sort using sort arrows at headers on work area assignment tab | C36: 1. Navigate to Opp dashboard 2. Click on connect workers button 3. Navigte to work area assignment tabs on connect workers page 4. Click on sort arrows at headers | D36: - user should be able to sort the details using sort arrows at headers
A37: Microplanning_35 | B37: Verify details on progress Tracker page | C37: 1. Navigate to Opp dashboard 2. Click on View progress map button 3. click on coverage see more button | D37: Following details are shown on progress tracker page: Ward saturation goal percentage Date filter Core metrics Metrics by Work Area Group Download buttons
A38: Microplanning_36 | B38: Verify core metrics details | C38: 1. Navigate to Opp dashboard 2. Click on View progress map button 3. click on coverage see more button | D38: - user should be able to download the core metric details - User should see the correct details of core metrics - Following details are shown: Ward name Expected Visit count Building count Work areas Approved visits % Visits completed WAs Visited %WAs Visited WAs Visited(Last Week) %WAs Visited(Last week) WAs EVC Reached %WAs EVC Reached WAs EVC Reached (Last Week) %WAs EVC Reached (Last Week) Buildings covered (WAs Visited) %Buildings covered (WAs Visited) Buildings covered (WAs Visited, Last week) %Buildings covered (WAs Visited, Last week) Buildings covered(WAs EVC Reached) %Buildings covered(WAs EVC Reached) Buildings covered(WAs EVC Reached, Last week) %Buildings covered(WAs EVC Reached, Last week) WA Visited : Visits Ratio WA Visited : Visits Ratio(Last week) WA EVC Reached : Visits Ratio WA EVC Reached : Visits Ratio (Last Week) Buildings EVC Reached : Visits Ratio Buildings EVC Reached : Visits Ratio (Last Week) Buildings Visited : Visits Ratio Buildings Visited : Visits Ratio (Last Week)
A39: Microplanning_37 | B39: Verify Metrics by work area group details | C39: 1. Navigate to Opp dashboard 2. Click on View progress map button 3. click on coverage see more button | D39: - user should be able to download the metrics by work area group details - User should see the correct details based on the progress made - Following details are shown Work Area Group Ward Expected Visit Count % Visits Completed % Visits Completed (Last Week) % WAs EVC Reached % WAs EVC Reached (Last Week) WA Visited : Visits Ratio WA Visited : Visits Ratio (Last Week)
A40: Microplanning_38 | B40: Verify date filter on progress tracker page | C40: 1. Navigate to Opp dashboard 2. Click on View progress map button 3. Click on coverage see more button 4. Apply date filters | D40: - User should be able to select the from and to dates
... A42: Microplanning_40 | B42: Verify that core metrics are updated based on the selected date range. | C42: 1. Navigate to Opp dashboard 2. Click on View progress map button 3. Click on coverage see more button 4. Apply date filters | D42: Core metrics data should get updated as per applied date
B43: Verify user is able to download the core metrics file

Sheet Test Tracker Horizontal
B1: <Feature_Name> or <Ticket Title> | E1: Key
E2: Pass | F2: Passed steps of Test Case
B3: - Feature Description - Test Domain - Feature Flag - (For master test plans) Last executed - <Anything specific to be added> | E3: Fail | F3: Failed steps of Test Case
E4: N/A | F4: Not applicable to your testing
E5: Blocking | F5: Failed and is a critical feature or cannot proceed with testing
A6: Name of Tester | B6: Start Date | C6: End Date | E6: Unanswered | F6: Unanswered/ blank test cases
A9: Tab | B9: =sheetName(2) | C9: =sheetName(3) | D9: =sheetName(4) | E9: =sheetName(5) | F9: =sheetName(6)
A10: <optional> Documentation Status
A11: Execution Status
A12: Duration
A14: Case Results (if none, displays as 0) | B14: {=countif(INDIRECT("'"&$B$9&"'!"&"D2:D100"), "Pass")} | C14: {=countif(INDIRECT("'"&$C$9&"'!"&"D2:D100"), "Pass")} | D14: {=countif(INDIRECT("'"&$D$9&"'!"&"D2:D100"), "Pass")} | E14: {=countif(INDIRECT("'"&$E$9&"'!"&"D2:D100"), "Pass")} | F14: {=countif(INDIRECT("'"&$F$9&"'!"&"D2:D100"), "Pass")}
B15: {=countif(INDIRECT("'"&$B$9&"'!"&"D2:D100"), "Fail")} | C15: {=countif(INDIRECT("'"&$C$9&"'!"&"D2:D100"), "Fail")} | D15: {=countif(INDIRECT("'"&$D$9&"'!"&"D2:D100"), "Fail")} | E15: {=countif(INDIRECT("'"&$E$9&"'!"&"D2:D100"), "Fail")} | F15: {=countif(INDIRECT("'"&$F$9&"'!"&"D2:D100"), "Fail")}
B16: {=countif(INDIRECT("'"&$B$9&"'!"&"D2:D100"), "N/A")} | C16: {=countif(INDIRECT("'"&$C$9&"'!"&"D2:D100"), "N/A")} | D16: {=countif(INDIRECT("'"&$D$9&"'!"&"D2:D100"), "N/A")} | E16: {=countif(INDIRECT("'"&$E$9&"'!"&"D2:D100"), "N/A")} | F16: {=countif(INDIRECT("'"&$F$9&"'!"&"D2:D100"), "N/A")}
B17: {=countif(INDIRECT("'"&$B$9&"'!"&"D2:D100"), "Blocking")} | C17: {=countif(INDIRECT("'"&$C$9&"'!"&"D2:D100"), "Blocking")} | D17: {=countif(INDIRECT("'"&$D$9&"'!"&"D2:D100"), "Blocking")} | E17: {=countif(INDIRECT("'"&$E$9&"'!"&"D2:D100"), "Blocking")} | F17: {=countif(INDIRECT("'"&$F$9&"'!"&"D2:D100"), "Blocking")}
B18: {=countif(INDIRECT("'"&$B$9&"'!"&"D2:D100"), "")} | C18: {=countif(INDIRECT("'"&$C$9&"'!"&"D2:D100"), "")} | D18: {=countif(INDIRECT("'"&$D$9&"'!"&"D2:D100"), "")} | E18: {=countif(INDIRECT("'"&$E$9&"'!"&"D2:D100"), "")} | F18: {=countif(INDIRECT("'"&$F$9&"'!"&"D2:D100"), "")}
A19: Total | B19: =sum(B14:B18) | C19: =sum(C14:C18) | D19: =sum(D14:D18) | E19: =sum(E14:E18) | F19: =sum(F14:F18)
A21: Ticket Summaries (if none, displays as #N/A) | B21: =IFERROR(__xludf.DUMMYFUNCTION("UNIQUE( FILTER( INDIRECT(""'""&$B$9&""'!""&""E2:E100"") , NOT(ISBLANK(INDIRECT(""'""&$B$9&""'!""&""E2:E100""))) ) )"),"#N/A") | C21: =IFERROR(__xludf.DUMMYFUNCTION("UNIQUE( FILTER( INDIRECT(""'""&$C$9&""'!""&""E2:E100"") , NOT(ISBLANK(INDIRECT(""'""&$C$9&""'!""&""E2:E100""))) ) )"),"#N/A") | D21: =IFERROR(__xludf.DUMMYFUNCTION("UNIQUE( FILTER(INDIRECT(""'""&$D$9&""'!""&""E2:E100"") , NOT(ISBLANK(INDIRECT(""'""&$D$9&""'!""&""E2:E100""))) ) )"),"#N/A") | E21: =IFERROR(__xludf.DUMMYFUNCTION("UNIQUE( FILTER(INDIRECT(""'""&$E$9&""'!""&""E2:E100"") , NOT(ISBLANK(INDIRECT(""'""&$E$9&""'!""&""E2:E100""))) ) )"),"#N/A") | F21: =IFERROR(__xludf.DUMMYFUNCTION("UNIQUE( FILTER(INDIRECT(""'""&$E$9&""'!""&""E2:E100"") , NOT(ISBLANK(INDIRECT(""'""&$E$9&""'!""&""E2:E100""))) ) )"),"#N/A")
